{"schema_version":"1","crate":"honki_tonks_zivilisationen","version":"0.5.5305","id":"0714382230321ae6","name":"BetriebssystemKonstanten","qualified_name":"BetriebssystemKonstanten","kind":"ada_package","location":{"file":"src/Globales/GlobaleKonstanten/Datentypen/BetriebssystemKonstanten.ads","line":5,"column":9},"code":"package BetriebssystemKonstanten","documentation":{"description":"Allgemein\nDie folgenden Zeichen sind Kopien aus Ada.Characters.Wide_Wide_Latin_1 und werden verwendet um das lokale Pragma \"pragma Restrictions (No_Implementation_Units)\" benutzen zu können!"},"constants":[{"id":"e5a7cb40258e752a","name":"ACK","qualified_name":"BetriebssystemKonstanten.ACK","kind":"ada_constant","location":{"file":"src/Globales/GlobaleKonstanten/Datentypen/BetriebssystemKonstanten.ads","line":16,"column":4},"code":"ACK : constant Wide_Wide_Character := Wide_Wide_Character'Val (6);"},{"id":"71137ba0d7a38db3","name":"BEL","qualified_name":"BetriebssystemKonstanten.BEL","kind":"ada_constant","location":{"file":"src/Globales/GlobaleKonstanten/Datentypen/BetriebssystemKonstanten.ads","line":17,"column":4},"code":"BEL : constant Wide_Wide_Character := Wide_Wide_Character'Val (7);"},{"id":"60e1500f61dcc082","name":"Bindestrich","qualified_name":"BetriebssystemKonstanten.Bindestrich","kind":"ada_constant","location":{"file":"src/Globales/GlobaleKonstanten/Datentypen/BetriebssystemKonstanten.ads","line":46,"column":4},"code":"Bindestrich : constant Wide_Wide_Character := '-';"},{"id":"76224a5e006ab7ce","name":"BS","qualified_name":"BetriebssystemKonstanten.BS","kind":"ada_constant","location":{"file":"src/Globales/GlobaleKonstanten/Datentypen/BetriebssystemKonstanten.ads","line":18,"column":4},"code":"BS : constant Wide_Wide_Character := Wide_Wide_Character'Val (8);"},{"id":"963f04850835f56e","name":"CAN","qualified_name":"BetriebssystemKonstanten.CAN","kind":"ada_constant","location":{"file":"src/Globales/GlobaleKonstanten/Datentypen/BetriebssystemKonstanten.ads","line":35,"column":4},"code":"CAN : constant Wide_Wide_Character := Wide_Wide_Character'Val (24);"},{"id":"f7b08c6f1b6ca9f4","name":"CR","qualified_name":"BetriebssystemKonstanten.CR","kind":"ada_constant","location":{"file":"src/Globales/GlobaleKonstanten/Datentypen/BetriebssystemKonstanten.ads","line":23,"column":4},"code":"CR : constant Wide_Wide_Character := Wide_Wide_Character'Val (13);"},{"id":"97cc86b6bf2b3c14","name":"DC1","qualified_name":"BetriebssystemKonstanten.DC1","kind":"ada_constant","location":{"file":"src/Globales/GlobaleKonstanten/Datentypen/BetriebssystemKonstanten.ads","line":28,"column":4},"code":"DC1 : constant Wide_Wide_Character := Wide_Wide_Character'Val (17);"},{"id":"6d0016f860c77a42","name":"DC2","qualified_name":"BetriebssystemKonstanten.DC2","kind":"ada_constant","location":{"file":"src/Globales/GlobaleKonstanten/Datentypen/BetriebssystemKonstanten.ads","line":29,"column":4},"code":"DC2 : constant Wide_Wide_Character := Wide_Wide_Character'Val (18);"},{"id":"2597f0e4c2a72d4d","name":"DC3","qualified_name":"BetriebssystemKonstanten.DC3","kind":"ada_constant","location":{"file":"src/Globales/GlobaleKonstanten/Datentypen/BetriebssystemKonstanten.ads","line":30,"column":4},"code":"DC3 : constant Wide_Wide_Character := Wide_Wide_Character'Val (19);"},{"id":"e12d93c2eca3957a","name":"DC4","qualified_name":"BetriebssystemKonstanten.DC4","kind":"ada_constant","location":{"file":"src/Globales/GlobaleKonstanten/Datentypen/BetriebssystemKonstanten.ads","line":31,"column":4},"code":"DC4 : constant Wide_Wide_Character := Wide_Wide_Character'Val (20);"},{"id":"c1957133c4782a83","name":"DEL","qualified_name":"BetriebssystemKonstanten.DEL","kind":"ada_constant","location":{"file":"src/Globales/GlobaleKonstanten/Datentypen/BetriebssystemKonstanten.ads","line":43,"column":4},"code":"DEL : constant Wide_Wide_Character := Wide_Wide_Character'Val (127);"},{"id":"2c2972f8258ed0eb","name":"DLE","qualified_name":"BetriebssystemKonstanten.DLE","kind":"ada_constant","location":{"file":"src/Globales/GlobaleKonstanten/Datentypen/BetriebssystemKonstanten.ads","line":27,"column":4},"code":"DLE : constant Wide_Wide_Character := Wide_Wide_Character'Val (16);"},{"id":"8f4f7c9afce52eda","name":"EM","qualified_name":"BetriebssystemKonstanten.EM","kind":"ada_constant","location":{"file":"src/Globales/GlobaleKonstanten/Datentypen/BetriebssystemKonstanten.ads","line":36,"column":4},"code":"EM : constant Wide_Wide_Character := Wide_Wide_Character'Val (25);"},{"id":"e486b0594764b146","name":"ENQ","qualified_name":"BetriebssystemKonstanten.ENQ","kind":"ada_constant","location":{"file":"src/Globales/GlobaleKonstanten/Datentypen/BetriebssystemKonstanten.ads","line":15,"column":4},"code":"ENQ : constant Wide_Wide_Character := Wide_Wide_Character'Val (5);"},{"id":"8a9f64151f5c282d","name":"EOT","qualified_name":"BetriebssystemKonstanten.EOT","kind":"ada_constant","location":{"file":"src/Globales/GlobaleKonstanten/Datentypen/BetriebssystemKonstanten.ads","line":14,"column":4},"code":"EOT : constant Wide_Wide_Character := Wide_Wide_Character'Val (4);"},{"id":"f93a95aca6b69c0c","name":"ESC","qualified_name":"BetriebssystemKonstanten.ESC","kind":"ada_constant","location":{"file":"src/Globales/GlobaleKonstanten/Datentypen/BetriebssystemKonstanten.ads","line":38,"column":4},"code":"ESC : constant Wide_Wide_Character := Wide_Wide_Character'Val (27);"},{"id":"79e3507be9209bdf","name":"ETB","qualified_name":"BetriebssystemKonstanten.ETB","kind":"ada_constant","location":{"file":"src/Globales/GlobaleKonstanten/Datentypen/BetriebssystemKonstanten.ads","line":34,"column":4},"code":"ETB : constant Wide_Wide_Character := Wide_Wide_Character'Val (23);"},{"id":"dd3cf2707eb51545","name":"ETX","qualified_name":"BetriebssystemKonstanten.ETX","kind":"ada_constant","location":{"file":"src/Globales/GlobaleKonstanten/Datentypen/BetriebssystemKonstanten.ads","line":13,"column":4},"code":"ETX : constant Wide_Wide_Character := Wide_Wide_Character'Val (3);"},{"id":"17fa5bffd049c759","name":"FF","qualified_name":"BetriebssystemKonstanten.FF","kind":"ada_constant","location":{"file":"src/Globales/GlobaleKonstanten/Datentypen/BetriebssystemKonstanten.ads","line":22,"column":4},"code":"FF : constant Wide_Wide_Character := Wide_Wide_Character'Val (12);"},{"id":"2bdc1296682bbaf7","name":"FS","qualified_name":"BetriebssystemKonstanten.FS","kind":"ada_constant","location":{"file":"src/Globales/GlobaleKonstanten/Datentypen/BetriebssystemKonstanten.ads","line":39,"column":4},"code":"FS : constant Wide_Wide_Character := Wide_Wide_Character'Val (28);"},{"id":"58c24a5adc458461","name":"GS","qualified_name":"BetriebssystemKonstanten.GS","kind":"ada_constant","location":{"file":"src/Globales/GlobaleKonstanten/Datentypen/BetriebssystemKonstanten.ads","line":40,"column":4},"code":"GS : constant Wide_Wide_Character := Wide_Wide_Character'Val (29);"},{"id":"b1114db535a5eee3","name":"HT","qualified_name":"BetriebssystemKonstanten.HT","kind":"ada_constant","location":{"file":"src/Globales/GlobaleKonstanten/Datentypen/BetriebssystemKonstanten.ads","line":19,"column":4},"code":"HT : constant Wide_Wide_Character := Wide_Wide_Character'Val (9);"},{"id":"08611768cb76cc88","name":"Leerzeichen","qualified_name":"BetriebssystemKonstanten.Leerzeichen","kind":"ada_constant","location":{"file":"src/Globales/GlobaleKonstanten/Datentypen/BetriebssystemKonstanten.ads","line":45,"column":4},"code":"Leerzeichen : constant Wide_Wide_Character := ' ';"},{"id":"c09564cefec62e8b","name":"LF","qualified_name":"BetriebssystemKonstanten.LF","kind":"ada_constant","location":{"file":"src/Globales/GlobaleKonstanten/Datentypen/BetriebssystemKonstanten.ads","line":20,"column":4},"code":"LF : constant Wide_Wide_Character := Wide_Wide_Character'Val (10);"},{"id":"2567aff7c3c6ff54","name":"NAK","qualified_name":"BetriebssystemKonstanten.NAK","kind":"ada_constant","location":{"file":"src/Globales/GlobaleKonstanten/Datentypen/BetriebssystemKonstanten.ads","line":32,"column":4},"code":"NAK : constant Wide_Wide_Character := Wide_Wide_Character'Val (21);"},{"id":"3d28292264a20538","name":"NUL","qualified_name":"BetriebssystemKonstanten.NUL","kind":"ada_constant","location":{"file":"src/Globales/GlobaleKonstanten/Datentypen/BetriebssystemKonstanten.ads","line":10,"column":4},"code":"NUL : constant Wide_Wide_Character := Wide_Wide_Character'Val (0);"},{"id":"7b582a06d4a878d8","name":"Punkt","qualified_name":"BetriebssystemKonstanten.Punkt","kind":"ada_constant","location":{"file":"src/Globales/GlobaleKonstanten/Datentypen/BetriebssystemKonstanten.ads","line":48,"column":4},"code":"Punkt : constant Wide_Wide_Character := '.';"},{"id":"7b6dda1c0605515b","name":"RS","qualified_name":"BetriebssystemKonstanten.RS","kind":"ada_constant","location":{"file":"src/Globales/GlobaleKonstanten/Datentypen/BetriebssystemKonstanten.ads","line":41,"column":4},"code":"RS : constant Wide_Wide_Character := Wide_Wide_Character'Val (30);"},{"id":"5dd6a127daadd61c","name":"SI","qualified_name":"BetriebssystemKonstanten.SI","kind":"ada_constant","location":{"file":"src/Globales/GlobaleKonstanten/Datentypen/BetriebssystemKonstanten.ads","line":25,"column":4},"code":"SI : constant Wide_Wide_Character := Wide_Wide_Character'Val (15);"},{"id":"e85625a3ed0c999e","name":"SO","qualified_name":"BetriebssystemKonstanten.SO","kind":"ada_constant","location":{"file":"src/Globales/GlobaleKonstanten/Datentypen/BetriebssystemKonstanten.ads","line":24,"column":4},"code":"SO : constant Wide_Wide_Character := Wide_Wide_Character'Val (14);"},{"id":"85ba740b9fde9eda","name":"SOH","qualified_name":"BetriebssystemKonstanten.SOH","kind":"ada_constant","location":{"file":"src/Globales/GlobaleKonstanten/Datentypen/BetriebssystemKonstanten.ads","line":11,"column":4},"code":"SOH : constant Wide_Wide_Character := Wide_Wide_Character'Val (1);"},{"id":"9c7be027d3249a10","name":"STX","qualified_name":"BetriebssystemKonstanten.STX","kind":"ada_constant","location":{"file":"src/Globales/GlobaleKonstanten/Datentypen/BetriebssystemKonstanten.ads","line":12,"column":4},"code":"STX : constant Wide_Wide_Character := Wide_Wide_Character'Val (2);"},{"id":"2d1c3cd9601ccac3","name":"SUB","qualified_name":"BetriebssystemKonstanten.SUB","kind":"ada_constant","location":{"file":"src/Globales/GlobaleKonstanten/Datentypen/BetriebssystemKonstanten.ads","line":37,"column":4},"code":"SUB : constant Wide_Wide_Character := Wide_Wide_Character'Val (26);"},{"id":"2b16b6e40b3b0d2d","name":"SYN","qualified_name":"BetriebssystemKonstanten.SYN","kind":"ada_constant","location":{"file":"src/Globales/GlobaleKonstanten/Datentypen/BetriebssystemKonstanten.ads","line":33,"column":4},"code":"SYN : constant Wide_Wide_Character := Wide_Wide_Character'Val (22);"},{"id":"4109f6cee19bc2aa","name":"Unterstrich","qualified_name":"BetriebssystemKonstanten.Unterstrich","kind":"ada_constant","location":{"file":"src/Globales/GlobaleKonstanten/Datentypen/BetriebssystemKonstanten.ads","line":47,"column":4},"code":"Unterstrich : constant Wide_Wide_Character := '_';"},{"id":"f577f3ea1861b3ff","name":"US","qualified_name":"BetriebssystemKonstanten.US","kind":"ada_constant","location":{"file":"src/Globales/GlobaleKonstanten/Datentypen/BetriebssystemKonstanten.ads","line":42,"column":4},"code":"US : constant Wide_Wide_Character := Wide_Wide_Character'Val (31);"},{"id":"ddcfdad54ecab4a1","name":"VerboteneNamen","qualified_name":"BetriebssystemKonstanten.VerboteneNamen","kind":"ada_constant","location":{"file":"src/Globales/GlobaleKonstanten/Datentypen/BetriebssystemKonstanten.ads","line":50,"column":4},"code":"VerboteneNamen : constant TextArrays.AllgemeinesTextArray (1 .. 2) := (\n                                                                       1 => To_Unbounded_Wide_Wide_String (Source => \".\"),\n                                                                       2 => To_Unbounded_Wide_Wide_String (Source => \"..\")\n                                                                      );","documentation":{"description":"Allgemein"}},{"id":"9128489229a95b7d","name":"VerboteneWindowsnamenGroß","qualified_name":"BetriebssystemKonstanten.VerboteneWindowsnamenGroß","kind":"ada_constant","location":{"file":"src/Globales/GlobaleKonstanten/Datentypen/BetriebssystemKonstanten.ads","line":65,"column":4},"code":"VerboteneWindowsnamenGroß : constant TextArrays.AllgemeinesTextArray (1 .. 25) := (\n                                                                                    1 => To_Unbounded_Wide_Wide_String (Source => \"AUX\"),\n                                                                                   …\n                                                                                   );"},{"id":"5e4bf9c4625865bf","name":"VerboteneWindowsnamenKlein","qualified_name":"BetriebssystemKonstanten.VerboteneWindowsnamenKlein","kind":"ada_constant","location":{"file":"src/Globales/GlobaleKonstanten/Datentypen/BetriebssystemKonstanten.ads","line":93,"column":4},"code":"VerboteneWindowsnamenKlein : constant TextArrays.AllgemeinesTextArray (VerboteneWindowsnamenGroß'Range) := (\n                                                                                                             1 => To_Unbounded_Wide_Wide_String (Source => \"aux\"),\n                                                                                                            …\n                                                                                                            );"},{"id":"d96852c05e36589d","name":"VT","qualified_name":"BetriebssystemKonstanten.VT","kind":"ada_constant","location":{"file":"src/Globales/GlobaleKonstanten/Datentypen/BetriebssystemKonstanten.ads","line":21,"column":4},"code":"VT : constant Wide_Wide_Character := Wide_Wide_Character'Val (11);"}]}