{"schema_version":"1","crate":"libsimpleio","version":"2.24736.1","id":"c20916ec0534c5c4","name":"libModbus","qualified_name":"libModbus","kind":"ada_package","location":{"file":"src/bindings/libmodbus.ads","line":28,"column":9},"code":"PACKAGE libModbus","documentation":{"description":"String actual parameters *MUST* be NUL terminated, e.g. \"FOO\" & ASCII.NUL"},"simple_types":[{"id":"a4a37ee8d9b927c1","name":"byte","qualified_name":"libModbus.byte","kind":"ada_simple_type","location":{"file":"src/bindings/libmodbus.ads","line":46,"column":8},"code":"TYPE byte IS MOD 2**8;"},{"id":"3822d38cf8d7af1c","name":"Context","qualified_name":"libModbus.Context","kind":"ada_simple_type","location":{"file":"src/bindings/libmodbus.ads","line":45,"column":8},"code":"TYPE Context IS NEW Interfaces.C.Strings.chars_ptr;"},{"id":"257ac1d5b5a14c6c","name":"word","qualified_name":"libModbus.word","kind":"ada_simple_type","location":{"file":"src/bindings/libmodbus.ads","line":47,"column":8},"code":"TYPE word IS MOD 2**16;"}],"array_types":[{"id":"57a2f8b2736f6c01","name":"bytearray","qualified_name":"libModbus.bytearray","kind":"ada_array_type","location":{"file":"src/bindings/libmodbus.ads","line":48,"column":8},"code":"TYPE bytearray IS ARRAY (Natural RANGE <>) OF byte;"},{"id":"84f71ef7a5726042","name":"wordarray","qualified_name":"libModbus.wordarray","kind":"ada_array_type","location":{"file":"src/bindings/libmodbus.ads","line":49,"column":8},"code":"TYPE wordarray IS ARRAY (Natural RANGE <>) OF word;"}],"constants":[{"id":"9311652d0028649d","name":"MODBUS_BROADCAST_ADDRESS","qualified_name":"libModbus.MODBUS_BROADCAST_ADDRESS","kind":"ada_constant","location":{"file":"src/bindings/libmodbus.ads","line":29,"column":3},"code":"MODBUS_BROADCAST_ADDRESS : CONSTANT :=  0;"},{"id":"f2e4ba0b65f6aaa2","name":"MODBUS_DEBUG_DISABLE","qualified_name":"libModbus.MODBUS_DEBUG_DISABLE","kind":"ada_constant","location":{"file":"src/bindings/libmodbus.ads","line":42,"column":3},"code":"MODBUS_DEBUG_DISABLE     : CONSTANT := 0;"},{"id":"fe3e8de2c85fa006","name":"MODBUS_DEBUG_ENABLE","qualified_name":"libModbus.MODBUS_DEBUG_ENABLE","kind":"ada_constant","location":{"file":"src/bindings/libmodbus.ads","line":43,"column":3},"code":"MODBUS_DEBUG_ENABLE      : CONSTANT := 1;"},{"id":"76ba8a16491eb9f2","name":"MODBUS_RTU_PARITY_EVEN","qualified_name":"libModbus.MODBUS_RTU_PARITY_EVEN","kind":"ada_constant","location":{"file":"src/bindings/libmodbus.ads","line":35,"column":3},"code":"MODBUS_RTU_PARITY_EVEN   : CONSTANT Character :=  'E';"},{"id":"8d9eba98e2a54012","name":"MODBUS_RTU_PARITY_NONE","qualified_name":"libModbus.MODBUS_RTU_PARITY_NONE","kind":"ada_constant","location":{"file":"src/bindings/libmodbus.ads","line":34,"column":3},"code":"MODBUS_RTU_PARITY_NONE   : CONSTANT Character :=  'N';"},{"id":"334d0eceb483cedc","name":"MODBUS_RTU_PARITY_ODD","qualified_name":"libModbus.MODBUS_RTU_PARITY_ODD","kind":"ada_constant","location":{"file":"src/bindings/libmodbus.ads","line":36,"column":3},"code":"MODBUS_RTU_PARITY_ODD    : CONSTANT Character :=  'O';"},{"id":"ef6071f84b0e7317","name":"MODBUS_RTU_RS232","qualified_name":"libModbus.MODBUS_RTU_RS232","kind":"ada_constant","location":{"file":"src/bindings/libmodbus.ads","line":31,"column":3},"code":"MODBUS_RTU_RS232         : CONSTANT :=  0;"},{"id":"f4fdabba52cd322c","name":"MODBUS_RTU_RS485","qualified_name":"libModbus.MODBUS_RTU_RS485","kind":"ada_constant","location":{"file":"src/bindings/libmodbus.ads","line":32,"column":3},"code":"MODBUS_RTU_RS485         : CONSTANT :=  1;"},{"id":"c1bc0ee5f019774c","name":"MODBUS_RTU_RTS_DOWN","qualified_name":"libModbus.MODBUS_RTU_RTS_DOWN","kind":"ada_constant","location":{"file":"src/bindings/libmodbus.ads","line":40,"column":3},"code":"MODBUS_RTU_RTS_DOWN      : CONSTANT :=  2;"},{"id":"6849fdd21d23151a","name":"MODBUS_RTU_RTS_NONE","qualified_name":"libModbus.MODBUS_RTU_RTS_NONE","kind":"ada_constant","location":{"file":"src/bindings/libmodbus.ads","line":38,"column":3},"code":"MODBUS_RTU_RTS_NONE      : CONSTANT :=  0;"},{"id":"7b13a8c779fe2be3","name":"MODBUS_RTU_RTS_UP","qualified_name":"libModbus.MODBUS_RTU_RTS_UP","kind":"ada_constant","location":{"file":"src/bindings/libmodbus.ads","line":39,"column":3},"code":"MODBUS_RTU_RTS_UP        : CONSTANT :=  1;"},{"id":"a2f6b3dfe0c046a5","name":"Null_Context","qualified_name":"libModbus.Null_Context","kind":"ada_constant","location":{"file":"src/bindings/libmodbus.ads","line":51,"column":3},"code":"Null_Context : CONSTANT Context := Context(Interfaces.C.Strings.Null_Ptr);"}],"subprograms":[{"id":"090f644c61888072","name":"error_message","qualified_name":"libModbus.error_message","kind":"ada_function","location":{"file":"src/bindings/libmodbus.ads","line":226,"column":12},"code":"FUNCTION error_message RETURN String"},{"id":"ac6a16650953dfbd","name":"modbus_close","qualified_name":"libModbus.modbus_close","kind":"ada_procedure","location":{"file":"src/bindings/libmodbus.ads","line":103,"column":13},"code":"PROCEDURE modbus_close\n (ctx : Context)"},{"id":"7365cfad4eed0c75","name":"modbus_connect","qualified_name":"libModbus.modbus_connect","kind":"ada_function","location":{"file":"src/bindings/libmodbus.ads","line":100,"column":12},"code":"FUNCTION modbus_connect\n (ctx : Context) RETURN Integer"},{"id":"b43f40b512f47e13","name":"modbus_flush","qualified_name":"libModbus.modbus_flush","kind":"ada_function","location":{"file":"src/bindings/libmodbus.ads","line":106,"column":12},"code":"FUNCTION modbus_flush\n (ctx : Context) RETURN Integer"},{"id":"5e99faa1504b7a45","name":"modbus_free","qualified_name":"libModbus.modbus_free","kind":"ada_procedure","location":{"file":"src/bindings/libmodbus.ads","line":68,"column":13},"code":"PROCEDURE modbus_free\n (ctx : Context)"},{"id":"23b56919f43cb993","name":"modbus_get_float","qualified_name":"libModbus.modbus_get_float","kind":"ada_function","location":{"file":"src/bindings/libmodbus.ads","line":180,"column":12},"code":"FUNCTION modbus_get_float\n (src : wordarray) RETURN Short_Float"},{"id":"4f762e0fbccd86ae","name":"modbus_get_float_abcd","qualified_name":"libModbus.modbus_get_float_abcd","kind":"ada_function","location":{"file":"src/bindings/libmodbus.ads","line":211,"column":12},"code":"FUNCTION modbus_get_float_abcd\n (src : wordarray) RETURN Short_Float"},{"id":"277c362a6086d89a","name":"modbus_get_float_badc","qualified_name":"libModbus.modbus_get_float_badc","kind":"ada_function","location":{"file":"src/bindings/libmodbus.ads","line":214,"column":12},"code":"FUNCTION modbus_get_float_badc\n (src : wordarray) RETURN Short_Float"},{"id":"099b36c22cbaf68f","name":"modbus_get_float_cdab","qualified_name":"libModbus.modbus_get_float_cdab","kind":"ada_function","location":{"file":"src/bindings/libmodbus.ads","line":217,"column":12},"code":"FUNCTION modbus_get_float_cdab\n (src : wordarray) RETURN Short_Float"},{"id":"7855b38742fc2344","name":"modbus_get_float_dcba","qualified_name":"libModbus.modbus_get_float_dcba","kind":"ada_function","location":{"file":"src/bindings/libmodbus.ads","line":220,"column":12},"code":"FUNCTION modbus_get_float_dcba\n (src : wordarray) RETURN Short_Float"},{"id":"32dde790299fb6a2","name":"modbus_new_rtu","qualified_name":"libModbus.modbus_new_rtu","kind":"ada_function","location":{"file":"src/bindings/libmodbus.ads","line":53,"column":12},"code":"FUNCTION modbus_new_rtu\n (device   : String;\n  baud     : Integer;\n  parity   : Character;\n  data_bit : Integer;\n  stop_bit : Integer) RETURN context"},{"id":"05e0415855378dd8","name":"modbus_new_tcp","qualified_name":"libModbus.modbus_new_tcp","kind":"ada_function","location":{"file":"src/bindings/libmodbus.ads","line":60,"column":12},"code":"FUNCTION modbus_new_tcp\n (addr : String;\n  port : Integer) RETURN context"},{"id":"fa35502d5aebe85a","name":"modbus_new_tcp_pi","qualified_name":"libModbus.modbus_new_tcp_pi","kind":"ada_function","location":{"file":"src/bindings/libmodbus.ads","line":64,"column":12},"code":"FUNCTION modbus_new_tcp_pi\n (node    : String;\n  service : String) RETURN context"},{"id":"af263af11a9c0608","name":"modbus_read_bits","qualified_name":"libModbus.modbus_read_bits","kind":"ada_function","location":{"file":"src/bindings/libmodbus.ads","line":116,"column":12},"code":"FUNCTION modbus_read_bits\n (ctx  : Context;\n  addr : Integer;\n  nb   : Integer;\n  dest : OUT bytearray) RETURN Integer","documentation":{"description":"aka coils","parameters":[{"name":"ctx","description":""},{"name":"addr","description":""},{"name":"nb","description":""},{"name":"dest","description":""}]}},{"id":"9e643275d0d8b902","name":"modbus_read_input_bits","qualified_name":"libModbus.modbus_read_input_bits","kind":"ada_function","location":{"file":"src/bindings/libmodbus.ads","line":122,"column":12},"code":"FUNCTION modbus_read_input_bits\n (ctx  : Context;\n  addr : Integer;\n  nb   : Integer;\n  dest : OUT bytearray) RETURN Integer","documentation":{"description":"aka discrete inputs","parameters":[{"name":"ctx","description":""},{"name":"addr","description":""},{"name":"nb","description":""},{"name":"dest","description":""}]}},{"id":"36f512f1de4edbce","name":"modbus_read_input_registers","qualified_name":"libModbus.modbus_read_input_registers","kind":"ada_function","location":{"file":"src/bindings/libmodbus.ads","line":134,"column":12},"code":"FUNCTION modbus_read_input_registers\n (ctx  : Context;\n  addr : Integer;\n  nb   : Integer;\n  dest : OUT wordarray) RETURN Integer"},{"id":"633cd67ef162fc88","name":"modbus_read_registers","qualified_name":"libModbus.modbus_read_registers","kind":"ada_function","location":{"file":"src/bindings/libmodbus.ads","line":128,"column":12},"code":"FUNCTION modbus_read_registers\n (ctx  : Context;\n  addr : Integer;\n  nb   : Integer;\n  dest : OUT wordarray) RETURN Integer","documentation":{"description":"aka holding registers","parameters":[{"name":"ctx","description":""},{"name":"addr","description":""},{"name":"nb","description":""},{"name":"dest","description":""}]}},{"id":"51ecd616d58f6cbe","name":"modbus_report_slave_id","qualified_name":"libModbus.modbus_report_slave_id","kind":"ada_function","location":{"file":"src/bindings/libmodbus.ads","line":109,"column":12},"code":"FUNCTION modbus_report_slave_id\n (ctx      : Context;\n  max_dest : Integer;\n  dest     : OUT bytearray) RETURN Integer"},{"id":"57ec68c87417d7e3","name":"modbus_rtu_get_rts","qualified_name":"libModbus.modbus_rtu_get_rts","kind":"ada_function","location":{"file":"src/bindings/libmodbus.ads","line":78,"column":12},"code":"FUNCTION modbus_rtu_get_rts\n (ctx : Context) RETURN Integer"},{"id":"4121982195db687a","name":"modbus_rtu_get_rts_delay","qualified_name":"libModbus.modbus_rtu_get_rts_delay","kind":"ada_function","location":{"file":"src/bindings/libmodbus.ads","line":85,"column":12},"code":"FUNCTION modbus_rtu_get_rts_delay\n (ctx : Context) RETURN Integer"},{"id":"fd52c9a9f0af617c","name":"modbus_rtu_get_serial_mode","qualified_name":"libModbus.modbus_rtu_get_serial_mode","kind":"ada_function","location":{"file":"src/bindings/libmodbus.ads","line":71,"column":12},"code":"FUNCTION modbus_rtu_get_serial_mode\n (ctx : Context) RETURN Integer"},{"id":"6c8b35c846c8d82f","name":"modbus_rtu_set_rts","qualified_name":"libModbus.modbus_rtu_set_rts","kind":"ada_function","location":{"file":"src/bindings/libmodbus.ads","line":81,"column":12},"code":"FUNCTION modbus_rtu_set_rts\n (ctx  : Context;\n  mode : Integer) RETURN Integer"},{"id":"6082319cc2c32ed7","name":"modbus_rtu_set_rts_Delay","qualified_name":"libModbus.modbus_rtu_set_rts_Delay","kind":"ada_function","location":{"file":"src/bindings/libmodbus.ads","line":88,"column":12},"code":"FUNCTION modbus_rtu_set_rts_Delay\n (ctx : Context;\n  us  : Integer) RETURN Integer"},{"id":"c29084dd32d1752b","name":"modbus_rtu_set_serial_mode","qualified_name":"libModbus.modbus_rtu_set_serial_mode","kind":"ada_function","location":{"file":"src/bindings/libmodbus.ads","line":74,"column":12},"code":"FUNCTION modbus_rtu_set_serial_mode\n (ctx  : Context;\n  mode : Integer) RETURN Integer"},{"id":"3418225b7abdda4d","name":"modbus_set_debug","qualified_name":"libModbus.modbus_set_debug","kind":"ada_function","location":{"file":"src/bindings/libmodbus.ads","line":96,"column":12},"code":"FUNCTION modbus_set_debug\n (ctx  : Context;\n  flag : Integer) RETURN Integer"},{"id":"fe54fcd1914d61fe","name":"modbus_set_float","qualified_name":"libModbus.modbus_set_float","kind":"ada_procedure","location":{"file":"src/bindings/libmodbus.ads","line":175,"column":13},"code":"PROCEDURE modbus_set_float\n (f    : Short_Float;\n  dest : OUT wordarray)"},{"id":"cd69eefc65474bf9","name":"modbus_set_float_abcd","qualified_name":"libModbus.modbus_set_float_abcd","kind":"ada_procedure","location":{"file":"src/bindings/libmodbus.ads","line":195,"column":13},"code":"PROCEDURE modbus_set_float_abcd\n (f    : Short_Float;\n  dest : OUT wordarray)"},{"id":"4ac2dfb380d2045d","name":"modbus_set_float_badc","qualified_name":"libModbus.modbus_set_float_badc","kind":"ada_procedure","location":{"file":"src/bindings/libmodbus.ads","line":199,"column":13},"code":"PROCEDURE modbus_set_float_badc\n (f    : Short_Float;\n  dest : OUT wordarray)"},{"id":"ccef75b4aa30f962","name":"modbus_set_float_cdab","qualified_name":"libModbus.modbus_set_float_cdab","kind":"ada_procedure","location":{"file":"src/bindings/libmodbus.ads","line":203,"column":13},"code":"PROCEDURE modbus_set_float_cdab\n (f    : Short_Float;\n  dest : OUT wordarray)"},{"id":"95762da808816ba5","name":"modbus_set_float_dcba","qualified_name":"libModbus.modbus_set_float_dcba","kind":"ada_procedure","location":{"file":"src/bindings/libmodbus.ads","line":207,"column":13},"code":"PROCEDURE modbus_set_float_dcba\n (f    : Short_Float;\n  dest : OUT wordarray)"},{"id":"bb5cc5d1f807df2f","name":"modbus_set_slave","qualified_name":"libModbus.modbus_set_slave","kind":"ada_function","location":{"file":"src/bindings/libmodbus.ads","line":92,"column":12},"code":"FUNCTION modbus_set_slave\n (ctx   : Context;\n  slave : Integer) RETURN Integer"},{"id":"cfc9ab2b7fecb4c2","name":"modbus_strerror","qualified_name":"libModbus.modbus_strerror","kind":"ada_function","location":{"file":"src/bindings/libmodbus.ads","line":223,"column":12},"code":"FUNCTION modbus_strerror\n (errnum : Integer) RETURN Interfaces.C.Strings.chars_ptr"},{"id":"c3c257df68fa438b","name":"modbus_write_and_read_registers","qualified_name":"libModbus.modbus_write_and_read_registers","kind":"ada_function","location":{"file":"src/bindings/libmodbus.ads","line":164,"column":12},"code":"FUNCTION modbus_write_and_read_registers\n (ctx        : Context;\n  write_addr : Integer;\n  write_nb   : Integer;\n  src        : wordarray;\n  read_addr  : Integer;\n  read_nb    : Integer;\n  dest       : OUT wordarray) RETURN Integer","documentation":{"description":"aka holding registers","parameters":[{"name":"ctx","description":""},{"name":"write_addr","description":""},{"name":"write_nb","description":""},{"name":"src","description":""},{"name":"read_addr","description":""},{"name":"read_nb","description":""},{"name":"dest","description":""}]}},{"id":"9045a0ece046b538","name":"modbus_write_bit","qualified_name":"libModbus.modbus_write_bit","kind":"ada_function","location":{"file":"src/bindings/libmodbus.ads","line":142,"column":12},"code":"FUNCTION modbus_write_bit\n (ctx    : Context;\n  addr   : Integer;\n  status : Integer) RETURN Integer","documentation":{"description":"aka coil","parameters":[{"name":"ctx","description":""},{"name":"addr","description":""},{"name":"status","description":""}]}},{"id":"8afa277ab3cff89e","name":"modbus_write_bits","qualified_name":"libModbus.modbus_write_bits","kind":"ada_function","location":{"file":"src/bindings/libmodbus.ads","line":147,"column":12},"code":"FUNCTION modbus_write_bits\n (ctx  : Context;\n  addr : Integer;\n  nb   : Integer;\n  src  : bytearray) RETURN Integer","documentation":{"description":"aka coils","parameters":[{"name":"ctx","description":""},{"name":"addr","description":""},{"name":"nb","description":""},{"name":"src","description":""}]}},{"id":"c46ca9db1411e3fe","name":"modbus_write_register","qualified_name":"libModbus.modbus_write_register","kind":"ada_function","location":{"file":"src/bindings/libmodbus.ads","line":153,"column":12},"code":"FUNCTION modbus_write_register\n (ctx   : Context;\n  addr  : Integer;\n  value : word) RETURN Integer","documentation":{"description":"aka holding register","parameters":[{"name":"ctx","description":""},{"name":"addr","description":""},{"name":"value","description":""}]}},{"id":"ec9bd27420b48144","name":"modbus_write_registers","qualified_name":"libModbus.modbus_write_registers","kind":"ada_function","location":{"file":"src/bindings/libmodbus.ads","line":158,"column":12},"code":"FUNCTION modbus_write_registers\n (ctx  : Context;\n  addr : Integer;\n  nb   : Integer;\n  src  : wordarray) RETURN Integer","documentation":{"description":"aka holding registers","parameters":[{"name":"ctx","description":""},{"name":"addr","description":""},{"name":"nb","description":""},{"name":"src","description":""}]}}]}