{"schema_version":"1","crate":"agpl","version":"1.0.0","id":"2ffee19d51952272","name":"Unicode.Names.Half_Full_Withdt_Forms","qualified_name":"Unicode.Names.Half_Full_Withdt_Forms","kind":"ada_package","location":{"file":"3rdparty/xmlada/unicode-names-half_full_withdt_forms.ads","line":4,"column":9},"code":"package Unicode.Names.Half_Full_Withdt_Forms","documentation":{"description":"This file is built automatically from data found on the\nunicode web site (http://www.unicode.org)"},"constants":[{"id":"93103d65994f687b","name":"Byte_Order_Mark","qualified_name":"Unicode.Names.Half_Full_Withdt_Forms.Byte_Order_Mark","kind":"ada_constant","location":{"file":"3rdparty/xmlada/unicode-names-half_full_withdt_forms.ads","line":6,"column":4},"code":"Byte_Order_Mark                         : constant Unicode_Char := 16#FEFF#;"},{"id":"bd7c5afa19f3412c","name":"Fullwidth_Ampersand","qualified_name":"Unicode.Names.Half_Full_Withdt_Forms.Fullwidth_Ampersand","kind":"ada_constant","location":{"file":"3rdparty/xmlada/unicode-names-half_full_withdt_forms.ads","line":12,"column":4},"code":"Fullwidth_Ampersand                     : constant Unicode_Char := 16#FF06#;"},{"id":"28ff6f7f36b153c1","name":"Fullwidth_Apostrophe","qualified_name":"Unicode.Names.Half_Full_Withdt_Forms.Fullwidth_Apostrophe","kind":"ada_constant","location":{"file":"3rdparty/xmlada/unicode-names-half_full_withdt_forms.ads","line":13,"column":4},"code":"Fullwidth_Apostrophe                    : constant Unicode_Char := 16#FF07#;"},{"id":"15d9dd99434c2aea","name":"Fullwidth_Asterisk","qualified_name":"Unicode.Names.Half_Full_Withdt_Forms.Fullwidth_Asterisk","kind":"ada_constant","location":{"file":"3rdparty/xmlada/unicode-names-half_full_withdt_forms.ads","line":16,"column":4},"code":"Fullwidth_Asterisk                      : constant Unicode_Char := 16#FF0A#;"},{"id":"51ed8782dc0f14a7","name":"Fullwidth_Broken_Bar","qualified_name":"Unicode.Names.Half_Full_Withdt_Forms.Fullwidth_Broken_Bar","kind":"ada_constant","location":{"file":"3rdparty/xmlada/unicode-names-half_full_withdt_forms.ads","line":222,"column":4},"code":"Fullwidth_Broken_Bar                    : constant Unicode_Char := 16#FFE4#;"},{"id":"dbd03917718ef75f","name":"Fullwidth_Cent_Sign","qualified_name":"Unicode.Names.Half_Full_Withdt_Forms.Fullwidth_Cent_Sign","kind":"ada_constant","location":{"file":"3rdparty/xmlada/unicode-names-half_full_withdt_forms.ads","line":218,"column":4},"code":"Fullwidth_Cent_Sign                     : constant Unicode_Char := 16#FFE0#;"},{"id":"65f1787a5cd92e41","name":"Fullwidth_Circumflex_Accent","qualified_name":"Unicode.Names.Half_Full_Withdt_Forms.Fullwidth_Circumflex_Accent","kind":"ada_constant","location":{"file":"3rdparty/xmlada/unicode-names-half_full_withdt_forms.ads","line":68,"column":4},"code":"Fullwidth_Circumflex_Accent             : constant Unicode_Char := 16#FF3E#;"},{"id":"66c0072ad139e3ca","name":"Fullwidth_Colon","qualified_name":"Unicode.Names.Half_Full_Withdt_Forms.Fullwidth_Colon","kind":"ada_constant","location":{"file":"3rdparty/xmlada/unicode-names-half_full_withdt_forms.ads","line":32,"column":4},"code":"Fullwidth_Colon                         : constant Unicode_Char := 16#FF1A#;"},{"id":"e207fb8c8f407500","name":"Fullwidth_Comma","qualified_name":"Unicode.Names.Half_Full_Withdt_Forms.Fullwidth_Comma","kind":"ada_constant","location":{"file":"3rdparty/xmlada/unicode-names-half_full_withdt_forms.ads","line":18,"column":4},"code":"Fullwidth_Comma                         : constant Unicode_Char := 16#FF0C#;"},{"id":"91a7386ec38c1bd0","name":"Fullwidth_Commercial_At","qualified_name":"Unicode.Names.Half_Full_Withdt_Forms.Fullwidth_Commercial_At","kind":"ada_constant","location":{"file":"3rdparty/xmlada/unicode-names-half_full_withdt_forms.ads","line":38,"column":4},"code":"Fullwidth_Commercial_At                 : constant Unicode_Char := 16#FF20#;"},{"id":"d87c3fb397993d1c","name":"Fullwidth_Digit_Eight","qualified_name":"Unicode.Names.Half_Full_Withdt_Forms.Fullwidth_Digit_Eight","kind":"ada_constant","location":{"file":"3rdparty/xmlada/unicode-names-half_full_withdt_forms.ads","line":30,"column":4},"code":"Fullwidth_Digit_Eight                   : constant Unicode_Char := 16#FF18#;"},{"id":"30a5658a4e77c5e6","name":"Fullwidth_Digit_Five","qualified_name":"Unicode.Names.Half_Full_Withdt_Forms.Fullwidth_Digit_Five","kind":"ada_constant","location":{"file":"3rdparty/xmlada/unicode-names-half_full_withdt_forms.ads","line":27,"column":4},"code":"Fullwidth_Digit_Five                    : constant Unicode_Char := 16#FF15#;"},{"id":"db5ec83e3ded04c0","name":"Fullwidth_Digit_Four","qualified_name":"Unicode.Names.Half_Full_Withdt_Forms.Fullwidth_Digit_Four","kind":"ada_constant","location":{"file":"3rdparty/xmlada/unicode-names-half_full_withdt_forms.ads","line":26,"column":4},"code":"Fullwidth_Digit_Four                    : constant Unicode_Char := 16#FF14#;"},{"id":"777049b38d361da1","name":"Fullwidth_Digit_Nine","qualified_name":"Unicode.Names.Half_Full_Withdt_Forms.Fullwidth_Digit_Nine","kind":"ada_constant","location":{"file":"3rdparty/xmlada/unicode-names-half_full_withdt_forms.ads","line":31,"column":4},"code":"Fullwidth_Digit_Nine                    : constant Unicode_Char := 16#FF19#;"},{"id":"80f0a18a8e448f5f","name":"Fullwidth_Digit_One","qualified_name":"Unicode.Names.Half_Full_Withdt_Forms.Fullwidth_Digit_One","kind":"ada_constant","location":{"file":"3rdparty/xmlada/unicode-names-half_full_withdt_forms.ads","line":23,"column":4},"code":"Fullwidth_Digit_One                     : constant Unicode_Char := 16#FF11#;"},{"id":"4bfd07b2e0246fbf","name":"Fullwidth_Digit_Seven","qualified_name":"Unicode.Names.Half_Full_Withdt_Forms.Fullwidth_Digit_Seven","kind":"ada_constant","location":{"file":"3rdparty/xmlada/unicode-names-half_full_withdt_forms.ads","line":29,"column":4},"code":"Fullwidth_Digit_Seven                   : constant Unicode_Char := 16#FF17#;"},{"id":"a3b3dad1f74ddc83","name":"Fullwidth_Digit_Six","qualified_name":"Unicode.Names.Half_Full_Withdt_Forms.Fullwidth_Digit_Six","kind":"ada_constant","location":{"file":"3rdparty/xmlada/unicode-names-half_full_withdt_forms.ads","line":28,"column":4},"code":"Fullwidth_Digit_Six                     : constant Unicode_Char := 16#FF16#;"},{"id":"24d3f00b34538686","name":"Fullwidth_Digit_Three","qualified_name":"Unicode.Names.Half_Full_Withdt_Forms.Fullwidth_Digit_Three","kind":"ada_constant","location":{"file":"3rdparty/xmlada/unicode-names-half_full_withdt_forms.ads","line":25,"column":4},"code":"Fullwidth_Digit_Three                   : constant Unicode_Char := 16#FF13#;"},{"id":"abdcfa7d62e6f969","name":"Fullwidth_Digit_Two","qualified_name":"Unicode.Names.Half_Full_Withdt_Forms.Fullwidth_Digit_Two","kind":"ada_constant","location":{"file":"3rdparty/xmlada/unicode-names-half_full_withdt_forms.ads","line":24,"column":4},"code":"Fullwidth_Digit_Two                     : constant Unicode_Char := 16#FF12#;"},{"id":"fa4d1edf342f1490","name":"Fullwidth_Digit_Zero","qualified_name":"Unicode.Names.Half_Full_Withdt_Forms.Fullwidth_Digit_Zero","kind":"ada_constant","location":{"file":"3rdparty/xmlada/unicode-names-half_full_withdt_forms.ads","line":22,"column":4},"code":"Fullwidth_Digit_Zero                    : constant Unicode_Char := 16#FF10#;"},{"id":"239174bd90d70d4d","name":"Fullwidth_Dollar_Sign","qualified_name":"Unicode.Names.Half_Full_Withdt_Forms.Fullwidth_Dollar_Sign","kind":"ada_constant","location":{"file":"3rdparty/xmlada/unicode-names-half_full_withdt_forms.ads","line":10,"column":4},"code":"Fullwidth_Dollar_Sign                   : constant Unicode_Char := 16#FF04#;"},{"id":"abe1e730c179060a","name":"Fullwidth_Equals_Sign","qualified_name":"Unicode.Names.Half_Full_Withdt_Forms.Fullwidth_Equals_Sign","kind":"ada_constant","location":{"file":"3rdparty/xmlada/unicode-names-half_full_withdt_forms.ads","line":35,"column":4},"code":"Fullwidth_Equals_Sign                   : constant Unicode_Char := 16#FF1D#;"},{"id":"e8bc583565a0cea8","name":"Fullwidth_Exclamation_Mark","qualified_name":"Unicode.Names.Half_Full_Withdt_Forms.Fullwidth_Exclamation_Mark","kind":"ada_constant","location":{"file":"3rdparty/xmlada/unicode-names-half_full_withdt_forms.ads","line":7,"column":4},"code":"Fullwidth_Exclamation_Mark              : constant Unicode_Char := 16#FF01#;"},{"id":"0bc308f8ed861614","name":"Fullwidth_Full_Stop","qualified_name":"Unicode.Names.Half_Full_Withdt_Forms.Fullwidth_Full_Stop","kind":"ada_constant","location":{"file":"3rdparty/xmlada/unicode-names-half_full_withdt_forms.ads","line":20,"column":4},"code":"Fullwidth_Full_Stop                     : constant Unicode_Char := 16#FF0E#;"},{"id":"585b8b220fc1089f","name":"Fullwidth_Grave_Accent","qualified_name":"Unicode.Names.Half_Full_Withdt_Forms.Fullwidth_Grave_Accent","kind":"ada_constant","location":{"file":"3rdparty/xmlada/unicode-names-half_full_withdt_forms.ads","line":70,"column":4},"code":"Fullwidth_Grave_Accent                  : constant Unicode_Char := 16#FF40#;"},{"id":"6164ee1727b22b81","name":"Fullwidth_Greater_Than_Sign","qualified_name":"Unicode.Names.Half_Full_Withdt_Forms.Fullwidth_Greater_Than_Sign","kind":"ada_constant","location":{"file":"3rdparty/xmlada/unicode-names-half_full_withdt_forms.ads","line":36,"column":4},"code":"Fullwidth_Greater_Than_Sign             : constant Unicode_Char := 16#FF1E#;"},{"id":"6d7c1040786e78d9","name":"Fullwidth_Hyphen_Minus","qualified_name":"Unicode.Names.Half_Full_Withdt_Forms.Fullwidth_Hyphen_Minus","kind":"ada_constant","location":{"file":"3rdparty/xmlada/unicode-names-half_full_withdt_forms.ads","line":19,"column":4},"code":"Fullwidth_Hyphen_Minus                  : constant Unicode_Char := 16#FF0D#;"},{"id":"d308044270407fc7","name":"Fullwidth_Latin_Capital_Letter_A","qualified_name":"Unicode.Names.Half_Full_Withdt_Forms.Fullwidth_Latin_Capital_Letter_A","kind":"ada_constant","location":{"file":"3rdparty/xmlada/unicode-names-half_full_withdt_forms.ads","line":39,"column":4},"code":"Fullwidth_Latin_Capital_Letter_A        : constant Unicode_Char := 16#FF21#;"},{"id":"5191f9b5e1479783","name":"Fullwidth_Latin_Capital_Letter_B","qualified_name":"Unicode.Names.Half_Full_Withdt_Forms.Fullwidth_Latin_Capital_Letter_B","kind":"ada_constant","location":{"file":"3rdparty/xmlada/unicode-names-half_full_withdt_forms.ads","line":40,"column":4},"code":"Fullwidth_Latin_Capital_Letter_B        : constant Unicode_Char := 16#FF22#;"},{"id":"f78813a12621efe5","name":"Fullwidth_Latin_Capital_Letter_C","qualified_name":"Unicode.Names.Half_Full_Withdt_Forms.Fullwidth_Latin_Capital_Letter_C","kind":"ada_constant","location":{"file":"3rdparty/xmlada/unicode-names-half_full_withdt_forms.ads","line":41,"column":4},"code":"Fullwidth_Latin_Capital_Letter_C        : constant Unicode_Char := 16#FF23#;"},{"id":"9bdf806419473ffb","name":"Fullwidth_Latin_Capital_Letter_D","qualified_name":"Unicode.Names.Half_Full_Withdt_Forms.Fullwidth_Latin_Capital_Letter_D","kind":"ada_constant","location":{"file":"3rdparty/xmlada/unicode-names-half_full_withdt_forms.ads","line":42,"column":4},"code":"Fullwidth_Latin_Capital_Letter_D        : constant Unicode_Char := 16#FF24#;"},{"id":"be820b1c53c5f987","name":"Fullwidth_Latin_Capital_Letter_E","qualified_name":"Unicode.Names.Half_Full_Withdt_Forms.Fullwidth_Latin_Capital_Letter_E","kind":"ada_constant","location":{"file":"3rdparty/xmlada/unicode-names-half_full_withdt_forms.ads","line":43,"column":4},"code":"Fullwidth_Latin_Capital_Letter_E        : constant Unicode_Char := 16#FF25#;"},{"id":"1dbba0702e2f9074","name":"Fullwidth_Latin_Capital_Letter_F","qualified_name":"Unicode.Names.Half_Full_Withdt_Forms.Fullwidth_Latin_Capital_Letter_F","kind":"ada_constant","location":{"file":"3rdparty/xmlada/unicode-names-half_full_withdt_forms.ads","line":44,"column":4},"code":"Fullwidth_Latin_Capital_Letter_F        : constant Unicode_Char := 16#FF26#;"},{"id":"effa97a4b514eaf9","name":"Fullwidth_Latin_Capital_Letter_G","qualified_name":"Unicode.Names.Half_Full_Withdt_Forms.Fullwidth_Latin_Capital_Letter_G","kind":"ada_constant","location":{"file":"3rdparty/xmlada/unicode-names-half_full_withdt_forms.ads","line":45,"column":4},"code":"Fullwidth_Latin_Capital_Letter_G        : constant Unicode_Char := 16#FF27#;"},{"id":"9a0ee9a877a1dc4f","name":"Fullwidth_Latin_Capital_Letter_H","qualified_name":"Unicode.Names.Half_Full_Withdt_Forms.Fullwidth_Latin_Capital_Letter_H","kind":"ada_constant","location":{"file":"3rdparty/xmlada/unicode-names-half_full_withdt_forms.ads","line":46,"column":4},"code":"Fullwidth_Latin_Capital_Letter_H        : constant Unicode_Char := 16#FF28#;"},{"id":"584424fa3bdb13bc","name":"Fullwidth_Latin_Capital_Letter_I","qualified_name":"Unicode.Names.Half_Full_Withdt_Forms.Fullwidth_Latin_Capital_Letter_I","kind":"ada_constant","location":{"file":"3rdparty/xmlada/unicode-names-half_full_withdt_forms.ads","line":47,"column":4},"code":"Fullwidth_Latin_Capital_Letter_I        : constant Unicode_Char := 16#FF29#;"},{"id":"576746d080e69521","name":"Fullwidth_Latin_Capital_Letter_J","qualified_name":"Unicode.Names.Half_Full_Withdt_Forms.Fullwidth_Latin_Capital_Letter_J","kind":"ada_constant","location":{"file":"3rdparty/xmlada/unicode-names-half_full_withdt_forms.ads","line":48,"column":4},"code":"Fullwidth_Latin_Capital_Letter_J        : constant Unicode_Char := 16#FF2A#;"},{"id":"d1aab3a295015009","name":"Fullwidth_Latin_Capital_Letter_K","qualified_name":"Unicode.Names.Half_Full_Withdt_Forms.Fullwidth_Latin_Capital_Letter_K","kind":"ada_constant","location":{"file":"3rdparty/xmlada/unicode-names-half_full_withdt_forms.ads","line":49,"column":4},"code":"Fullwidth_Latin_Capital_Letter_K        : constant Unicode_Char := 16#FF2B#;"},{"id":"a2fc2acb18a1967e","name":"Fullwidth_Latin_Capital_Letter_L","qualified_name":"Unicode.Names.Half_Full_Withdt_Forms.Fullwidth_Latin_Capital_Letter_L","kind":"ada_constant","location":{"file":"3rdparty/xmlada/unicode-names-half_full_withdt_forms.ads","line":50,"column":4},"code":"Fullwidth_Latin_Capital_Letter_L        : constant Unicode_Char := 16#FF2C#;"},{"id":"151d14691b1f951f","name":"Fullwidth_Latin_Capital_Letter_M","qualified_name":"Unicode.Names.Half_Full_Withdt_Forms.Fullwidth_Latin_Capital_Letter_M","kind":"ada_constant","location":{"file":"3rdparty/xmlada/unicode-names-half_full_withdt_forms.ads","line":51,"column":4},"code":"Fullwidth_Latin_Capital_Letter_M        : constant Unicode_Char := 16#FF2D#;"},{"id":"6c8434e1e73e48d5","name":"Fullwidth_Latin_Capital_Letter_N","qualified_name":"Unicode.Names.Half_Full_Withdt_Forms.Fullwidth_Latin_Capital_Letter_N","kind":"ada_constant","location":{"file":"3rdparty/xmlada/unicode-names-half_full_withdt_forms.ads","line":52,"column":4},"code":"Fullwidth_Latin_Capital_Letter_N        : constant Unicode_Char := 16#FF2E#;"},{"id":"40be07f8628d3a45","name":"Fullwidth_Latin_Capital_Letter_O","qualified_name":"Unicode.Names.Half_Full_Withdt_Forms.Fullwidth_Latin_Capital_Letter_O","kind":"ada_constant","location":{"file":"3rdparty/xmlada/unicode-names-half_full_withdt_forms.ads","line":53,"column":4},"code":"Fullwidth_Latin_Capital_Letter_O        : constant Unicode_Char := 16#FF2F#;"},{"id":"94a540c549ffc4fb","name":"Fullwidth_Latin_Capital_Letter_P","qualified_name":"Unicode.Names.Half_Full_Withdt_Forms.Fullwidth_Latin_Capital_Letter_P","kind":"ada_constant","location":{"file":"3rdparty/xmlada/unicode-names-half_full_withdt_forms.ads","line":54,"column":4},"code":"Fullwidth_Latin_Capital_Letter_P        : constant Unicode_Char := 16#FF30#;"},{"id":"749143828b67292f","name":"Fullwidth_Latin_Capital_Letter_Q","qualified_name":"Unicode.Names.Half_Full_Withdt_Forms.Fullwidth_Latin_Capital_Letter_Q","kind":"ada_constant","location":{"file":"3rdparty/xmlada/unicode-names-half_full_withdt_forms.ads","line":55,"column":4},"code":"Fullwidth_Latin_Capital_Letter_Q        : constant Unicode_Char := 16#FF31#;"},{"id":"42cf037664fd1eea","name":"Fullwidth_Latin_Capital_Letter_R","qualified_name":"Unicode.Names.Half_Full_Withdt_Forms.Fullwidth_Latin_Capital_Letter_R","kind":"ada_constant","location":{"file":"3rdparty/xmlada/unicode-names-half_full_withdt_forms.ads","line":56,"column":4},"code":"Fullwidth_Latin_Capital_Letter_R        : constant Unicode_Char := 16#FF32#;"},{"id":"dedb01912393a68a","name":"Fullwidth_Latin_Capital_Letter_S","qualified_name":"Unicode.Names.Half_Full_Withdt_Forms.Fullwidth_Latin_Capital_Letter_S","kind":"ada_constant","location":{"file":"3rdparty/xmlada/unicode-names-half_full_withdt_forms.ads","line":57,"column":4},"code":"Fullwidth_Latin_Capital_Letter_S        : constant Unicode_Char := 16#FF33#;"},{"id":"317a8fa96b0cd4fa","name":"Fullwidth_Latin_Capital_Letter_T","qualified_name":"Unicode.Names.Half_Full_Withdt_Forms.Fullwidth_Latin_Capital_Letter_T","kind":"ada_constant","location":{"file":"3rdparty/xmlada/unicode-names-half_full_withdt_forms.ads","line":58,"column":4},"code":"Fullwidth_Latin_Capital_Letter_T        : constant Unicode_Char := 16#FF34#;"},{"id":"d164d2c02d96816b","name":"Fullwidth_Latin_Capital_Letter_U","qualified_name":"Unicode.Names.Half_Full_Withdt_Forms.Fullwidth_Latin_Capital_Letter_U","kind":"ada_constant","location":{"file":"3rdparty/xmlada/unicode-names-half_full_withdt_forms.ads","line":59,"column":4},"code":"Fullwidth_Latin_Capital_Letter_U        : constant Unicode_Char := 16#FF35#;"},{"id":"1cb4d048fb7fb704","name":"Fullwidth_Latin_Capital_Letter_V","qualified_name":"Unicode.Names.Half_Full_Withdt_Forms.Fullwidth_Latin_Capital_Letter_V","kind":"ada_constant","location":{"file":"3rdparty/xmlada/unicode-names-half_full_withdt_forms.ads","line":60,"column":4},"code":"Fullwidth_Latin_Capital_Letter_V        : constant Unicode_Char := 16#FF36#;"},{"id":"1927d5d1e14c58f0","name":"Fullwidth_Latin_Capital_Letter_W","qualified_name":"Unicode.Names.Half_Full_Withdt_Forms.Fullwidth_Latin_Capital_Letter_W","kind":"ada_constant","location":{"file":"3rdparty/xmlada/unicode-names-half_full_withdt_forms.ads","line":61,"column":4},"code":"Fullwidth_Latin_Capital_Letter_W        : constant Unicode_Char := 16#FF37#;"},{"id":"ffb9862b76d36092","name":"Fullwidth_Latin_Capital_Letter_X","qualified_name":"Unicode.Names.Half_Full_Withdt_Forms.Fullwidth_Latin_Capital_Letter_X","kind":"ada_constant","location":{"file":"3rdparty/xmlada/unicode-names-half_full_withdt_forms.ads","line":62,"column":4},"code":"Fullwidth_Latin_Capital_Letter_X        : constant Unicode_Char := 16#FF38#;"},{"id":"6e5d382930ea1e8d","name":"Fullwidth_Latin_Capital_Letter_Y","qualified_name":"Unicode.Names.Half_Full_Withdt_Forms.Fullwidth_Latin_Capital_Letter_Y","kind":"ada_constant","location":{"file":"3rdparty/xmlada/unicode-names-half_full_withdt_forms.ads","line":63,"column":4},"code":"Fullwidth_Latin_Capital_Letter_Y        : constant Unicode_Char := 16#FF39#;"},{"id":"d7478ea51bff0209","name":"Fullwidth_Latin_Capital_Letter_Z","qualified_name":"Unicode.Names.Half_Full_Withdt_Forms.Fullwidth_Latin_Capital_Letter_Z","kind":"ada_constant","location":{"file":"3rdparty/xmlada/unicode-names-half_full_withdt_forms.ads","line":64,"column":4},"code":"Fullwidth_Latin_Capital_Letter_Z        : constant Unicode_Char := 16#FF3A#;"},{"id":"1ee1f7a1594ddd11","name":"Fullwidth_Latin_Small_Letter_A","qualified_name":"Unicode.Names.Half_Full_Withdt_Forms.Fullwidth_Latin_Small_Letter_A","kind":"ada_constant","location":{"file":"3rdparty/xmlada/unicode-names-half_full_withdt_forms.ads","line":71,"column":4},"code":"Fullwidth_Latin_Small_Letter_A          : constant Unicode_Char := 16#FF41#;"},{"id":"5c44b314f43145b6","name":"Fullwidth_Latin_Small_Letter_B","qualified_name":"Unicode.Names.Half_Full_Withdt_Forms.Fullwidth_Latin_Small_Letter_B","kind":"ada_constant","location":{"file":"3rdparty/xmlada/unicode-names-half_full_withdt_forms.ads","line":72,"column":4},"code":"Fullwidth_Latin_Small_Letter_B          : constant Unicode_Char := 16#FF42#;"},{"id":"8f3488462048df54","name":"Fullwidth_Latin_Small_Letter_C","qualified_name":"Unicode.Names.Half_Full_Withdt_Forms.Fullwidth_Latin_Small_Letter_C","kind":"ada_constant","location":{"file":"3rdparty/xmlada/unicode-names-half_full_withdt_forms.ads","line":73,"column":4},"code":"Fullwidth_Latin_Small_Letter_C          : constant Unicode_Char := 16#FF43#;"},{"id":"ee8b197affd41161","name":"Fullwidth_Latin_Small_Letter_D","qualified_name":"Unicode.Names.Half_Full_Withdt_Forms.Fullwidth_Latin_Small_Letter_D","kind":"ada_constant","location":{"file":"3rdparty/xmlada/unicode-names-half_full_withdt_forms.ads","line":74,"column":4},"code":"Fullwidth_Latin_Small_Letter_D          : constant Unicode_Char := 16#FF44#;"},{"id":"f8640a85a63efe5b","name":"Fullwidth_Latin_Small_Letter_E","qualified_name":"Unicode.Names.Half_Full_Withdt_Forms.Fullwidth_Latin_Small_Letter_E","kind":"ada_constant","location":{"file":"3rdparty/xmlada/unicode-names-half_full_withdt_forms.ads","line":75,"column":4},"code":"Fullwidth_Latin_Small_Letter_E          : constant Unicode_Char := 16#FF45#;"},{"id":"1b0311b271a90b3f","name":"Fullwidth_Latin_Small_Letter_F","qualified_name":"Unicode.Names.Half_Full_Withdt_Forms.Fullwidth_Latin_Small_Letter_F","kind":"ada_constant","location":{"file":"3rdparty/xmlada/unicode-names-half_full_withdt_forms.ads","line":76,"column":4},"code":"Fullwidth_Latin_Small_Letter_F          : constant Unicode_Char := 16#FF46#;"},{"id":"360ece6992f48390","name":"Fullwidth_Latin_Small_Letter_G","qualified_name":"Unicode.Names.Half_Full_Withdt_Forms.Fullwidth_Latin_Small_Letter_G","kind":"ada_constant","location":{"file":"3rdparty/xmlada/unicode-names-half_full_withdt_forms.ads","line":77,"column":4},"code":"Fullwidth_Latin_Small_Letter_G          : constant Unicode_Char := 16#FF47#;"},{"id":"5a51563d7937d4c6","name":"Fullwidth_Latin_Small_Letter_H","qualified_name":"Unicode.Names.Half_Full_Withdt_Forms.Fullwidth_Latin_Small_Letter_H","kind":"ada_constant","location":{"file":"3rdparty/xmlada/unicode-names-half_full_withdt_forms.ads","line":78,"column":4},"code":"Fullwidth_Latin_Small_Letter_H          : constant Unicode_Char := 16#FF48#;"},{"id":"98f2bfd3d5fe6776","name":"Fullwidth_Latin_Small_Letter_I","qualified_name":"Unicode.Names.Half_Full_Withdt_Forms.Fullwidth_Latin_Small_Letter_I","kind":"ada_constant","location":{"file":"3rdparty/xmlada/unicode-names-half_full_withdt_forms.ads","line":79,"column":4},"code":"Fullwidth_Latin_Small_Letter_I          : constant Unicode_Char := 16#FF49#;"},{"id":"122256ad1866444a","name":"Fullwidth_Latin_Small_Letter_J","qualified_name":"Unicode.Names.Half_Full_Withdt_Forms.Fullwidth_Latin_Small_Letter_J","kind":"ada_constant","location":{"file":"3rdparty/xmlada/unicode-names-half_full_withdt_forms.ads","line":80,"column":4},"code":"Fullwidth_Latin_Small_Letter_J          : constant Unicode_Char := 16#FF4A#;"},{"id":"ed87d4bd69602d82","name":"Fullwidth_Latin_Small_Letter_K","qualified_name":"Unicode.Names.Half_Full_Withdt_Forms.Fullwidth_Latin_Small_Letter_K","kind":"ada_constant","location":{"file":"3rdparty/xmlada/unicode-names-half_full_withdt_forms.ads","line":81,"column":4},"code":"Fullwidth_Latin_Small_Letter_K          : constant Unicode_Char := 16#FF4B#;"},{"id":"ce6cc332bd586ee1","name":"Fullwidth_Latin_Small_Letter_L","qualified_name":"Unicode.Names.Half_Full_Withdt_Forms.Fullwidth_Latin_Small_Letter_L","kind":"ada_constant","location":{"file":"3rdparty/xmlada/unicode-names-half_full_withdt_forms.ads","line":82,"column":4},"code":"Fullwidth_Latin_Small_Letter_L          : constant Unicode_Char := 16#FF4C#;"},{"id":"a02834f0b8f93ccf","name":"Fullwidth_Latin_Small_Letter_M","qualified_name":"Unicode.Names.Half_Full_Withdt_Forms.Fullwidth_Latin_Small_Letter_M","kind":"ada_constant","location":{"file":"3rdparty/xmlada/unicode-names-half_full_withdt_forms.ads","line":83,"column":4},"code":"Fullwidth_Latin_Small_Letter_M          : constant Unicode_Char := 16#FF4D#;"},{"id":"2f81c9cb2ee6491b","name":"Fullwidth_Latin_Small_Letter_N","qualified_name":"Unicode.Names.Half_Full_Withdt_Forms.Fullwidth_Latin_Small_Letter_N","kind":"ada_constant","location":{"file":"3rdparty/xmlada/unicode-names-half_full_withdt_forms.ads","line":84,"column":4},"code":"Fullwidth_Latin_Small_Letter_N          : constant Unicode_Char := 16#FF4E#;"},{"id":"8d2d69f8a220162c","name":"Fullwidth_Latin_Small_Letter_O","qualified_name":"Unicode.Names.Half_Full_Withdt_Forms.Fullwidth_Latin_Small_Letter_O","kind":"ada_constant","location":{"file":"3rdparty/xmlada/unicode-names-half_full_withdt_forms.ads","line":85,"column":4},"code":"Fullwidth_Latin_Small_Letter_O          : constant Unicode_Char := 16#FF4F#;"},{"id":"98d17106f528b95c","name":"Fullwidth_Latin_Small_Letter_P","qualified_name":"Unicode.Names.Half_Full_Withdt_Forms.Fullwidth_Latin_Small_Letter_P","kind":"ada_constant","location":{"file":"3rdparty/xmlada/unicode-names-half_full_withdt_forms.ads","line":86,"column":4},"code":"Fullwidth_Latin_Small_Letter_P          : constant Unicode_Char := 16#FF50#;"},{"id":"1b541fed380c1853","name":"Fullwidth_Latin_Small_Letter_Q","qualified_name":"Unicode.Names.Half_Full_Withdt_Forms.Fullwidth_Latin_Small_Letter_Q","kind":"ada_constant","location":{"file":"3rdparty/xmlada/unicode-names-half_full_withdt_forms.ads","line":87,"column":4},"code":"Fullwidth_Latin_Small_Letter_Q          : constant Unicode_Char := 16#FF51#;"},{"id":"0fcae6d1a83703f6","name":"Fullwidth_Latin_Small_Letter_R","qualified_name":"Unicode.Names.Half_Full_Withdt_Forms.Fullwidth_Latin_Small_Letter_R","kind":"ada_constant","location":{"file":"3rdparty/xmlada/unicode-names-half_full_withdt_forms.ads","line":88,"column":4},"code":"Fullwidth_Latin_Small_Letter_R          : constant Unicode_Char := 16#FF52#;"},{"id":"42e5333006de0446","name":"Fullwidth_Latin_Small_Letter_S","qualified_name":"Unicode.Names.Half_Full_Withdt_Forms.Fullwidth_Latin_Small_Letter_S","kind":"ada_constant","location":{"file":"3rdparty/xmlada/unicode-names-half_full_withdt_forms.ads","line":89,"column":4},"code":"Fullwidth_Latin_Small_Letter_S          : constant Unicode_Char := 16#FF53#;"},{"id":"746328bfd521f504","name":"Fullwidth_Latin_Small_Letter_T","qualified_name":"Unicode.Names.Half_Full_Withdt_Forms.Fullwidth_Latin_Small_Letter_T","kind":"ada_constant","location":{"file":"3rdparty/xmlada/unicode-names-half_full_withdt_forms.ads","line":90,"column":4},"code":"Fullwidth_Latin_Small_Letter_T          : constant Unicode_Char := 16#FF54#;"},{"id":"d4006c1d75c0dc83","name":"Fullwidth_Latin_Small_Letter_U","qualified_name":"Unicode.Names.Half_Full_Withdt_Forms.Fullwidth_Latin_Small_Letter_U","kind":"ada_constant","location":{"file":"3rdparty/xmlada/unicode-names-half_full_withdt_forms.ads","line":91,"column":4},"code":"Fullwidth_Latin_Small_Letter_U          : constant Unicode_Char := 16#FF55#;"},{"id":"7ab5a19ae82439eb","name":"Fullwidth_Latin_Small_Letter_V","qualified_name":"Unicode.Names.Half_Full_Withdt_Forms.Fullwidth_Latin_Small_Letter_V","kind":"ada_constant","location":{"file":"3rdparty/xmlada/unicode-names-half_full_withdt_forms.ads","line":92,"column":4},"code":"Fullwidth_Latin_Small_Letter_V          : constant Unicode_Char := 16#FF56#;"},{"id":"ac85d574d9e5f5b5","name":"Fullwidth_Latin_Small_Letter_W","qualified_name":"Unicode.Names.Half_Full_Withdt_Forms.Fullwidth_Latin_Small_Letter_W","kind":"ada_constant","location":{"file":"3rdparty/xmlada/unicode-names-half_full_withdt_forms.ads","line":93,"column":4},"code":"Fullwidth_Latin_Small_Letter_W          : constant Unicode_Char := 16#FF57#;"},{"id":"7c9e4da3c4387be9","name":"Fullwidth_Latin_Small_Letter_X","qualified_name":"Unicode.Names.Half_Full_Withdt_Forms.Fullwidth_Latin_Small_Letter_X","kind":"ada_constant","location":{"file":"3rdparty/xmlada/unicode-names-half_full_withdt_forms.ads","line":94,"column":4},"code":"Fullwidth_Latin_Small_Letter_X          : constant Unicode_Char := 16#FF58#;"},{"id":"150653b0e105b149","name":"Fullwidth_Latin_Small_Letter_Y","qualified_name":"Unicode.Names.Half_Full_Withdt_Forms.Fullwidth_Latin_Small_Letter_Y","kind":"ada_constant","location":{"file":"3rdparty/xmlada/unicode-names-half_full_withdt_forms.ads","line":95,"column":4},"code":"Fullwidth_Latin_Small_Letter_Y          : constant Unicode_Char := 16#FF59#;"},{"id":"7ff42f2edb98e22a","name":"Fullwidth_Latin_Small_Letter_Z","qualified_name":"Unicode.Names.Half_Full_Withdt_Forms.Fullwidth_Latin_Small_Letter_Z","kind":"ada_constant","location":{"file":"3rdparty/xmlada/unicode-names-half_full_withdt_forms.ads","line":96,"column":4},"code":"Fullwidth_Latin_Small_Letter_Z          : constant Unicode_Char := 16#FF5A#;"},{"id":"e145fdeeeb9ffbb2","name":"Fullwidth_Left_Curly_Bracket","qualified_name":"Unicode.Names.Half_Full_Withdt_Forms.Fullwidth_Left_Curly_Bracket","kind":"ada_constant","location":{"file":"3rdparty/xmlada/unicode-names-half_full_withdt_forms.ads","line":97,"column":4},"code":"Fullwidth_Left_Curly_Bracket            : constant Unicode_Char := 16#FF5B#;"},{"id":"1ef043db632160a4","name":"Fullwidth_Left_Parenthesis","qualified_name":"Unicode.Names.Half_Full_Withdt_Forms.Fullwidth_Left_Parenthesis","kind":"ada_constant","location":{"file":"3rdparty/xmlada/unicode-names-half_full_withdt_forms.ads","line":14,"column":4},"code":"Fullwidth_Left_Parenthesis              : constant Unicode_Char := 16#FF08#;"},{"id":"7429a3db42ab0ba0","name":"Fullwidth_Left_Square_Bracket","qualified_name":"Unicode.Names.Half_Full_Withdt_Forms.Fullwidth_Left_Square_Bracket","kind":"ada_constant","location":{"file":"3rdparty/xmlada/unicode-names-half_full_withdt_forms.ads","line":65,"column":4},"code":"Fullwidth_Left_Square_Bracket           : constant Unicode_Char := 16#FF3B#;"},{"id":"cd37908631c27b82","name":"Fullwidth_Less_Than_Sign","qualified_name":"Unicode.Names.Half_Full_Withdt_Forms.Fullwidth_Less_Than_Sign","kind":"ada_constant","location":{"file":"3rdparty/xmlada/unicode-names-half_full_withdt_forms.ads","line":34,"column":4},"code":"Fullwidth_Less_Than_Sign                : constant Unicode_Char := 16#FF1C#;"},{"id":"311dbb6434875923","name":"Fullwidth_Low_Line","qualified_name":"Unicode.Names.Half_Full_Withdt_Forms.Fullwidth_Low_Line","kind":"ada_constant","location":{"file":"3rdparty/xmlada/unicode-names-half_full_withdt_forms.ads","line":69,"column":4},"code":"Fullwidth_Low_Line                      : constant Unicode_Char := 16#FF3F#;"},{"id":"9870cc7085f2acad","name":"Fullwidth_Macron","qualified_name":"Unicode.Names.Half_Full_Withdt_Forms.Fullwidth_Macron","kind":"ada_constant","location":{"file":"3rdparty/xmlada/unicode-names-half_full_withdt_forms.ads","line":221,"column":4},"code":"Fullwidth_Macron                        : constant Unicode_Char := 16#FFE3#;"},{"id":"cf01792dce6aa6cd","name":"Fullwidth_Not_Sign","qualified_name":"Unicode.Names.Half_Full_Withdt_Forms.Fullwidth_Not_Sign","kind":"ada_constant","location":{"file":"3rdparty/xmlada/unicode-names-half_full_withdt_forms.ads","line":220,"column":4},"code":"Fullwidth_Not_Sign                      : constant Unicode_Char := 16#FFE2#;"},{"id":"86b67ffb6a72da8a","name":"Fullwidth_Number_Sign","qualified_name":"Unicode.Names.Half_Full_Withdt_Forms.Fullwidth_Number_Sign","kind":"ada_constant","location":{"file":"3rdparty/xmlada/unicode-names-half_full_withdt_forms.ads","line":9,"column":4},"code":"Fullwidth_Number_Sign                   : constant Unicode_Char := 16#FF03#;"},{"id":"6de603d97142df20","name":"Fullwidth_Percent_Sign","qualified_name":"Unicode.Names.Half_Full_Withdt_Forms.Fullwidth_Percent_Sign","kind":"ada_constant","location":{"file":"3rdparty/xmlada/unicode-names-half_full_withdt_forms.ads","line":11,"column":4},"code":"Fullwidth_Percent_Sign                  : constant Unicode_Char := 16#FF05#;"},{"id":"f88cacd66337ae81","name":"Fullwidth_Plus_Sign","qualified_name":"Unicode.Names.Half_Full_Withdt_Forms.Fullwidth_Plus_Sign","kind":"ada_constant","location":{"file":"3rdparty/xmlada/unicode-names-half_full_withdt_forms.ads","line":17,"column":4},"code":"Fullwidth_Plus_Sign                     : constant Unicode_Char := 16#FF0B#;"},{"id":"e4e0af4319f74b63","name":"Fullwidth_Pound_Sign","qualified_name":"Unicode.Names.Half_Full_Withdt_Forms.Fullwidth_Pound_Sign","kind":"ada_constant","location":{"file":"3rdparty/xmlada/unicode-names-half_full_withdt_forms.ads","line":219,"column":4},"code":"Fullwidth_Pound_Sign                    : constant Unicode_Char := 16#FFE1#;"},{"id":"ab8041d94f375f17","name":"Fullwidth_Question_Mark","qualified_name":"Unicode.Names.Half_Full_Withdt_Forms.Fullwidth_Question_Mark","kind":"ada_constant","location":{"file":"3rdparty/xmlada/unicode-names-half_full_withdt_forms.ads","line":37,"column":4},"code":"Fullwidth_Question_Mark                 : constant Unicode_Char := 16#FF1F#;"},{"id":"2e123e52995a4b60","name":"Fullwidth_Quotation_Mark","qualified_name":"Unicode.Names.Half_Full_Withdt_Forms.Fullwidth_Quotation_Mark","kind":"ada_constant","location":{"file":"3rdparty/xmlada/unicode-names-half_full_withdt_forms.ads","line":8,"column":4},"code":"Fullwidth_Quotation_Mark                : constant Unicode_Char := 16#FF02#;"},{"id":"c3e0fda213c2edbb","name":"Fullwidth_Reverse_Solidus","qualified_name":"Unicode.Names.Half_Full_Withdt_Forms.Fullwidth_Reverse_Solidus","kind":"ada_constant","location":{"file":"3rdparty/xmlada/unicode-names-half_full_withdt_forms.ads","line":66,"column":4},"code":"Fullwidth_Reverse_Solidus               : constant Unicode_Char := 16#FF3C#;"},{"id":"667307541328ae83","name":"Fullwidth_Right_Curly_Bracket","qualified_name":"Unicode.Names.Half_Full_Withdt_Forms.Fullwidth_Right_Curly_Bracket","kind":"ada_constant","location":{"file":"3rdparty/xmlada/unicode-names-half_full_withdt_forms.ads","line":99,"column":4},"code":"Fullwidth_Right_Curly_Bracket           : constant Unicode_Char := 16#FF5D#;"},{"id":"3c186622c0dd58f2","name":"Fullwidth_Right_Parenthesis","qualified_name":"Unicode.Names.Half_Full_Withdt_Forms.Fullwidth_Right_Parenthesis","kind":"ada_constant","location":{"file":"3rdparty/xmlada/unicode-names-half_full_withdt_forms.ads","line":15,"column":4},"code":"Fullwidth_Right_Parenthesis             : constant Unicode_Char := 16#FF09#;"},{"id":"f402eeb4db574169","name":"Fullwidth_Right_Square_Bracket","qualified_name":"Unicode.Names.Half_Full_Withdt_Forms.Fullwidth_Right_Square_Bracket","kind":"ada_constant","location":{"file":"3rdparty/xmlada/unicode-names-half_full_withdt_forms.ads","line":67,"column":4},"code":"Fullwidth_Right_Square_Bracket          : constant Unicode_Char := 16#FF3D#;"},{"id":"d8e108d7ab69ae34","name":"Fullwidth_Semicolon","qualified_name":"Unicode.Names.Half_Full_Withdt_Forms.Fullwidth_Semicolon","kind":"ada_constant","location":{"file":"3rdparty/xmlada/unicode-names-half_full_withdt_forms.ads","line":33,"column":4},"code":"Fullwidth_Semicolon                     : constant Unicode_Char := 16#FF1B#;"},{"id":"d759c0ca335d4ba8","name":"Fullwidth_Solidus","qualified_name":"Unicode.Names.Half_Full_Withdt_Forms.Fullwidth_Solidus","kind":"ada_constant","location":{"file":"3rdparty/xmlada/unicode-names-half_full_withdt_forms.ads","line":21,"column":4},"code":"Fullwidth_Solidus                       : constant Unicode_Char := 16#FF0F#;"},{"id":"5755b6f9a9a90937","name":"Fullwidth_Tilde","qualified_name":"Unicode.Names.Half_Full_Withdt_Forms.Fullwidth_Tilde","kind":"ada_constant","location":{"file":"3rdparty/xmlada/unicode-names-half_full_withdt_forms.ads","line":100,"column":4},"code":"Fullwidth_Tilde                         : constant Unicode_Char := 16#FF5E#;"},{"id":"037367bc714e1e70","name":"Fullwidth_Vertical_Line","qualified_name":"Unicode.Names.Half_Full_Withdt_Forms.Fullwidth_Vertical_Line","kind":"ada_constant","location":{"file":"3rdparty/xmlada/unicode-names-half_full_withdt_forms.ads","line":98,"column":4},"code":"Fullwidth_Vertical_Line                 : constant Unicode_Char := 16#FF5C#;"},{"id":"7e6f339babef6e66","name":"Fullwidth_Won_Sign","qualified_name":"Unicode.Names.Half_Full_Withdt_Forms.Fullwidth_Won_Sign","kind":"ada_constant","location":{"file":"3rdparty/xmlada/unicode-names-half_full_withdt_forms.ads","line":224,"column":4},"code":"Fullwidth_Won_Sign                      : constant Unicode_Char := 16#FFE6#;"},{"id":"a91c15823c8739e0","name":"Fullwidth_Yen_Sign","qualified_name":"Unicode.Names.Half_Full_Withdt_Forms.Fullwidth_Yen_Sign","kind":"ada_constant","location":{"file":"3rdparty/xmlada/unicode-names-half_full_withdt_forms.ads","line":223,"column":4},"code":"Fullwidth_Yen_Sign                      : constant Unicode_Char := 16#FFE5#;"},{"id":"660beb0c8bc4402a","name":"Halfwidth_Black_Square","qualified_name":"Unicode.Names.Half_Full_Withdt_Forms.Halfwidth_Black_Square","kind":"ada_constant","location":{"file":"3rdparty/xmlada/unicode-names-half_full_withdt_forms.ads","line":230,"column":4},"code":"Halfwidth_Black_Square                  : constant Unicode_Char := 16#FFED#;"},{"id":"a5ab3cb6218afe7c","name":"Halfwidth_Downwards_Arrow","qualified_name":"Unicode.Names.Half_Full_Withdt_Forms.Halfwidth_Downwards_Arrow","kind":"ada_constant","location":{"file":"3rdparty/xmlada/unicode-names-half_full_withdt_forms.ads","line":229,"column":4},"code":"Halfwidth_Downwards_Arrow               : constant Unicode_Char := 16#FFEC#;"},{"id":"18d5936eaa402f32","name":"Halfwidth_Forms_Light_Vertical","qualified_name":"Unicode.Names.Half_Full_Withdt_Forms.Halfwidth_Forms_Light_Vertical","kind":"ada_constant","location":{"file":"3rdparty/xmlada/unicode-names-half_full_withdt_forms.ads","line":225,"column":4},"code":"Halfwidth_Forms_Light_Vertical          : constant Unicode_Char := 16#FFE8#;"},{"id":"09b981e88518d56e","name":"Halfwidth_Hangul_Filler","qualified_name":"Unicode.Names.Half_Full_Withdt_Forms.Halfwidth_Hangul_Filler","kind":"ada_constant","location":{"file":"3rdparty/xmlada/unicode-names-half_full_withdt_forms.ads","line":166,"column":4},"code":"Halfwidth_Hangul_Filler                 : constant Unicode_Char := 16#FFA0#;"},{"id":"4c50c7daaaf0b5f9","name":"Halfwidth_Hangul_Letter_A","qualified_name":"Unicode.Names.Half_Full_Withdt_Forms.Halfwidth_Hangul_Letter_A","kind":"ada_constant","location":{"file":"3rdparty/xmlada/unicode-names-half_full_withdt_forms.ads","line":197,"column":4},"code":"Halfwidth_Hangul_Letter_A               : constant Unicode_Char := 16#FFC2#;"},{"id":"68061de7478f30f2","name":"Halfwidth_Hangul_Letter_Ae","qualified_name":"Unicode.Names.Half_Full_Withdt_Forms.Halfwidth_Hangul_Letter_Ae","kind":"ada_constant","location":{"file":"3rdparty/xmlada/unicode-names-half_full_withdt_forms.ads","line":198,"column":4},"code":"Halfwidth_Hangul_Letter_Ae              : constant Unicode_Char := 16#FFC3#;"},{"id":"88717b84ef88181e","name":"Halfwidth_Hangul_Letter_Chieuch","qualified_name":"Unicode.Names.Half_Full_Withdt_Forms.Halfwidth_Hangul_Letter_Chieuch","kind":"ada_constant","location":{"file":"3rdparty/xmlada/unicode-names-half_full_withdt_forms.ads","line":192,"column":4},"code":"Halfwidth_Hangul_Letter_Chieuch         : constant Unicode_Char := 16#FFBA#;"},{"id":"a73e67c8fcccac92","name":"Halfwidth_Hangul_Letter_Cieuc","qualified_name":"Unicode.Names.Half_Full_Withdt_Forms.Halfwidth_Hangul_Letter_Cieuc","kind":"ada_constant","location":{"file":"3rdparty/xmlada/unicode-names-half_full_withdt_forms.ads","line":190,"column":4},"code":"Halfwidth_Hangul_Letter_Cieuc           : constant Unicode_Char := 16#FFB8#;"},{"id":"562128588107b831","name":"Halfwidth_Hangul_Letter_E","qualified_name":"Unicode.Names.Half_Full_Withdt_Forms.Halfwidth_Hangul_Letter_E","kind":"ada_constant","location":{"file":"3rdparty/xmlada/unicode-names-half_full_withdt_forms.ads","line":202,"column":4},"code":"Halfwidth_Hangul_Letter_E               : constant Unicode_Char := 16#FFC7#;"},{"id":"c4b1dcea87d6989c","name":"Halfwidth_Hangul_Letter_Eo","qualified_name":"Unicode.Names.Half_Full_Withdt_Forms.Halfwidth_Hangul_Letter_Eo","kind":"ada_constant","location":{"file":"3rdparty/xmlada/unicode-names-half_full_withdt_forms.ads","line":201,"column":4},"code":"Halfwidth_Hangul_Letter_Eo              : constant Unicode_Char := 16#FFC6#;"},{"id":"77bbec6e3710d28a","name":"Halfwidth_Hangul_Letter_Eu","qualified_name":"Unicode.Names.Half_Full_Withdt_Forms.Halfwidth_Hangul_Letter_Eu","kind":"ada_constant","location":{"file":"3rdparty/xmlada/unicode-names-half_full_withdt_forms.ads","line":215,"column":4},"code":"Halfwidth_Hangul_Letter_Eu              : constant Unicode_Char := 16#FFDA#;"},{"id":"1a449b9cb2b34944","name":"Halfwidth_Hangul_Letter_Hieuh","qualified_name":"Unicode.Names.Half_Full_Withdt_Forms.Halfwidth_Hangul_Letter_Hieuh","kind":"ada_constant","location":{"file":"3rdparty/xmlada/unicode-names-half_full_withdt_forms.ads","line":196,"column":4},"code":"Halfwidth_Hangul_Letter_Hieuh           : constant Unicode_Char := 16#FFBE#;"},{"id":"392dbbaa5821b895","name":"Halfwidth_Hangul_Letter_I","qualified_name":"Unicode.Names.Half_Full_Withdt_Forms.Halfwidth_Hangul_Letter_I","kind":"ada_constant","location":{"file":"3rdparty/xmlada/unicode-names-half_full_withdt_forms.ads","line":217,"column":4},"code":"Halfwidth_Hangul_Letter_I               : constant Unicode_Char := 16#FFDC#;"},{"id":"fb57abf62ecd1ce2","name":"Halfwidth_Hangul_Letter_Ieung","qualified_name":"Unicode.Names.Half_Full_Withdt_Forms.Halfwidth_Hangul_Letter_Ieung","kind":"ada_constant","location":{"file":"3rdparty/xmlada/unicode-names-half_full_withdt_forms.ads","line":189,"column":4},"code":"Halfwidth_Hangul_Letter_Ieung           : constant Unicode_Char := 16#FFB7#;"},{"id":"f30f3500af438721","name":"Halfwidth_Hangul_Letter_Khieukh","qualified_name":"Unicode.Names.Half_Full_Withdt_Forms.Halfwidth_Hangul_Letter_Khieukh","kind":"ada_constant","location":{"file":"3rdparty/xmlada/unicode-names-half_full_withdt_forms.ads","line":193,"column":4},"code":"Halfwidth_Hangul_Letter_Khieukh         : constant Unicode_Char := 16#FFBB#;"},{"id":"0a5fc4ce60420022","name":"Halfwidth_Hangul_Letter_Kiyeok","qualified_name":"Unicode.Names.Half_Full_Withdt_Forms.Halfwidth_Hangul_Letter_Kiyeok","kind":"ada_constant","location":{"file":"3rdparty/xmlada/unicode-names-half_full_withdt_forms.ads","line":167,"column":4},"code":"Halfwidth_Hangul_Letter_Kiyeok          : constant Unicode_Char := 16#FFA1#;"},{"id":"d6d78a74e3762dd4","name":"Halfwidth_Hangul_Letter_Kiyeok_Sios","qualified_name":"Unicode.Names.Half_Full_Withdt_Forms.Halfwidth_Hangul_Letter_Kiyeok_Sios","kind":"ada_constant","location":{"file":"3rdparty/xmlada/unicode-names-half_full_withdt_forms.ads","line":169,"column":4},"code":"Halfwidth_Hangul_Letter_Kiyeok_Sios     : constant Unicode_Char := 16#FFA3#;"},{"id":"fd348a53cd98a54f","name":"Halfwidth_Hangul_Letter_Mieum","qualified_name":"Unicode.Names.Half_Full_Withdt_Forms.Halfwidth_Hangul_Letter_Mieum","kind":"ada_constant","location":{"file":"3rdparty/xmlada/unicode-names-half_full_withdt_forms.ads","line":183,"column":4},"code":"Halfwidth_Hangul_Letter_Mieum           : constant Unicode_Char := 16#FFB1#;"},{"id":"59809bb83a90f066","name":"Halfwidth_Hangul_Letter_Nieun","qualified_name":"Unicode.Names.Half_Full_Withdt_Forms.Halfwidth_Hangul_Letter_Nieun","kind":"ada_constant","location":{"file":"3rdparty/xmlada/unicode-names-half_full_withdt_forms.ads","line":170,"column":4},"code":"Halfwidth_Hangul_Letter_Nieun           : constant Unicode_Char := 16#FFA4#;"},{"id":"2193f57275de5f18","name":"Halfwidth_Hangul_Letter_Nieun_Cieuc","qualified_name":"Unicode.Names.Half_Full_Withdt_Forms.Halfwidth_Hangul_Letter_Nieun_Cieuc","kind":"ada_constant","location":{"file":"3rdparty/xmlada/unicode-names-half_full_withdt_forms.ads","line":171,"column":4},"code":"Halfwidth_Hangul_Letter_Nieun_Cieuc     : constant Unicode_Char := 16#FFA5#;"},{"id":"6f1c64700661b4f6","name":"Halfwidth_Hangul_Letter_Nieun_Hieuh","qualified_name":"Unicode.Names.Half_Full_Withdt_Forms.Halfwidth_Hangul_Letter_Nieun_Hieuh","kind":"ada_constant","location":{"file":"3rdparty/xmlada/unicode-names-half_full_withdt_forms.ads","line":172,"column":4},"code":"Halfwidth_Hangul_Letter_Nieun_Hieuh     : constant Unicode_Char := 16#FFA6#;"},{"id":"cf656a68c70cef62","name":"Halfwidth_Hangul_Letter_O","qualified_name":"Unicode.Names.Half_Full_Withdt_Forms.Halfwidth_Hangul_Letter_O","kind":"ada_constant","location":{"file":"3rdparty/xmlada/unicode-names-half_full_withdt_forms.ads","line":205,"column":4},"code":"Halfwidth_Hangul_Letter_O               : constant Unicode_Char := 16#FFCC#;"},{"id":"84bd6042aa4edfa9","name":"Halfwidth_Hangul_Letter_Oe","qualified_name":"Unicode.Names.Half_Full_Withdt_Forms.Halfwidth_Hangul_Letter_Oe","kind":"ada_constant","location":{"file":"3rdparty/xmlada/unicode-names-half_full_withdt_forms.ads","line":208,"column":4},"code":"Halfwidth_Hangul_Letter_Oe              : constant Unicode_Char := 16#FFCF#;"},{"id":"5f45396c469dec51","name":"Halfwidth_Hangul_Letter_Phieuph","qualified_name":"Unicode.Names.Half_Full_Withdt_Forms.Halfwidth_Hangul_Letter_Phieuph","kind":"ada_constant","location":{"file":"3rdparty/xmlada/unicode-names-half_full_withdt_forms.ads","line":195,"column":4},"code":"Halfwidth_Hangul_Letter_Phieuph         : constant Unicode_Char := 16#FFBD#;"},{"id":"b77396d53bb34b74","name":"Halfwidth_Hangul_Letter_Pieup","qualified_name":"Unicode.Names.Half_Full_Withdt_Forms.Halfwidth_Hangul_Letter_Pieup","kind":"ada_constant","location":{"file":"3rdparty/xmlada/unicode-names-half_full_withdt_forms.ads","line":184,"column":4},"code":"Halfwidth_Hangul_Letter_Pieup           : constant Unicode_Char := 16#FFB2#;"},{"id":"5cb1882d6888ca77","name":"Halfwidth_Hangul_Letter_Pieup_Sios","qualified_name":"Unicode.Names.Half_Full_Withdt_Forms.Halfwidth_Hangul_Letter_Pieup_Sios","kind":"ada_constant","location":{"file":"3rdparty/xmlada/unicode-names-half_full_withdt_forms.ads","line":186,"column":4},"code":"Halfwidth_Hangul_Letter_Pieup_Sios      : constant Unicode_Char := 16#FFB4#;"},{"id":"ef6f9b3518188b81","name":"Halfwidth_Hangul_Letter_Rieul","qualified_name":"Unicode.Names.Half_Full_Withdt_Forms.Halfwidth_Hangul_Letter_Rieul","kind":"ada_constant","location":{"file":"3rdparty/xmlada/unicode-names-half_full_withdt_forms.ads","line":175,"column":4},"code":"Halfwidth_Hangul_Letter_Rieul           : constant Unicode_Char := 16#FFA9#;"},{"id":"ae646d739c59cfd1","name":"Halfwidth_Hangul_Letter_Rieul_Hieuh","qualified_name":"Unicode.Names.Half_Full_Withdt_Forms.Halfwidth_Hangul_Letter_Rieul_Hieuh","kind":"ada_constant","location":{"file":"3rdparty/xmlada/unicode-names-half_full_withdt_forms.ads","line":182,"column":4},"code":"Halfwidth_Hangul_Letter_Rieul_Hieuh     : constant Unicode_Char := 16#FFB0#;"},{"id":"74aa393aa7f7d73c","name":"Halfwidth_Hangul_Letter_Rieul_Kiyeok","qualified_name":"Unicode.Names.Half_Full_Withdt_Forms.Halfwidth_Hangul_Letter_Rieul_Kiyeok","kind":"ada_constant","location":{"file":"3rdparty/xmlada/unicode-names-half_full_withdt_forms.ads","line":176,"column":4},"code":"Halfwidth_Hangul_Letter_Rieul_Kiyeok    : constant Unicode_Char := 16#FFAA#;"},{"id":"8d30c5996a799190","name":"Halfwidth_Hangul_Letter_Rieul_Mieum","qualified_name":"Unicode.Names.Half_Full_Withdt_Forms.Halfwidth_Hangul_Letter_Rieul_Mieum","kind":"ada_constant","location":{"file":"3rdparty/xmlada/unicode-names-half_full_withdt_forms.ads","line":177,"column":4},"code":"Halfwidth_Hangul_Letter_Rieul_Mieum     : constant Unicode_Char := 16#FFAB#;"},{"id":"cdaf5a7ce6684c33","name":"Halfwidth_Hangul_Letter_Rieul_Phieuph","qualified_name":"Unicode.Names.Half_Full_Withdt_Forms.Halfwidth_Hangul_Letter_Rieul_Phieuph","kind":"ada_constant","location":{"file":"3rdparty/xmlada/unicode-names-half_full_withdt_forms.ads","line":181,"column":4},"code":"Halfwidth_Hangul_Letter_Rieul_Phieuph   : constant Unicode_Char := 16#FFAF#;"},{"id":"50f4bf9a9e780213","name":"Halfwidth_Hangul_Letter_Rieul_Pieup","qualified_name":"Unicode.Names.Half_Full_Withdt_Forms.Halfwidth_Hangul_Letter_Rieul_Pieup","kind":"ada_constant","location":{"file":"3rdparty/xmlada/unicode-names-half_full_withdt_forms.ads","line":178,"column":4},"code":"Halfwidth_Hangul_Letter_Rieul_Pieup     : constant Unicode_Char := 16#FFAC#;"},{"id":"eed9854b2cf2ffa2","name":"Halfwidth_Hangul_Letter_Rieul_Sios","qualified_name":"Unicode.Names.Half_Full_Withdt_Forms.Halfwidth_Hangul_Letter_Rieul_Sios","kind":"ada_constant","location":{"file":"3rdparty/xmlada/unicode-names-half_full_withdt_forms.ads","line":179,"column":4},"code":"Halfwidth_Hangul_Letter_Rieul_Sios      : constant Unicode_Char := 16#FFAD#;"},{"id":"574b015f1a40d0d6","name":"Halfwidth_Hangul_Letter_Rieul_Thieuth","qualified_name":"Unicode.Names.Half_Full_Withdt_Forms.Halfwidth_Hangul_Letter_Rieul_Thieuth","kind":"ada_constant","location":{"file":"3rdparty/xmlada/unicode-names-half_full_withdt_forms.ads","line":180,"column":4},"code":"Halfwidth_Hangul_Letter_Rieul_Thieuth   : constant Unicode_Char := 16#FFAE#;"},{"id":"994f49a5ba0b8b9b","name":"Halfwidth_Hangul_Letter_Sios","qualified_name":"Unicode.Names.Half_Full_Withdt_Forms.Halfwidth_Hangul_Letter_Sios","kind":"ada_constant","location":{"file":"3rdparty/xmlada/unicode-names-half_full_withdt_forms.ads","line":187,"column":4},"code":"Halfwidth_Hangul_Letter_Sios            : constant Unicode_Char := 16#FFB5#;"},{"id":"45ab1527c130031a","name":"Halfwidth_Hangul_Letter_Ssangcieuc","qualified_name":"Unicode.Names.Half_Full_Withdt_Forms.Halfwidth_Hangul_Letter_Ssangcieuc","kind":"ada_constant","location":{"file":"3rdparty/xmlada/unicode-names-half_full_withdt_forms.ads","line":191,"column":4},"code":"Halfwidth_Hangul_Letter_Ssangcieuc      : constant Unicode_Char := 16#FFB9#;"},{"id":"d0150d82a6bf6c5e","name":"Halfwidth_Hangul_Letter_Ssangkiyeok","qualified_name":"Unicode.Names.Half_Full_Withdt_Forms.Halfwidth_Hangul_Letter_Ssangkiyeok","kind":"ada_constant","location":{"file":"3rdparty/xmlada/unicode-names-half_full_withdt_forms.ads","line":168,"column":4},"code":"Halfwidth_Hangul_Letter_Ssangkiyeok     : constant Unicode_Char := 16#FFA2#;"},{"id":"0af5edef89e5ea7c","name":"Halfwidth_Hangul_Letter_Ssangpieup","qualified_name":"Unicode.Names.Half_Full_Withdt_Forms.Halfwidth_Hangul_Letter_Ssangpieup","kind":"ada_constant","location":{"file":"3rdparty/xmlada/unicode-names-half_full_withdt_forms.ads","line":185,"column":4},"code":"Halfwidth_Hangul_Letter_Ssangpieup      : constant Unicode_Char := 16#FFB3#;"},{"id":"6c06d71b0d128824","name":"Halfwidth_Hangul_Letter_Ssangsios","qualified_name":"Unicode.Names.Half_Full_Withdt_Forms.Halfwidth_Hangul_Letter_Ssangsios","kind":"ada_constant","location":{"file":"3rdparty/xmlada/unicode-names-half_full_withdt_forms.ads","line":188,"column":4},"code":"Halfwidth_Hangul_Letter_Ssangsios       : constant Unicode_Char := 16#FFB6#;"},{"id":"1305b39fbf2442ea","name":"Halfwidth_Hangul_Letter_Ssangtikeut","qualified_name":"Unicode.Names.Half_Full_Withdt_Forms.Halfwidth_Hangul_Letter_Ssangtikeut","kind":"ada_constant","location":{"file":"3rdparty/xmlada/unicode-names-half_full_withdt_forms.ads","line":174,"column":4},"code":"Halfwidth_Hangul_Letter_Ssangtikeut     : constant Unicode_Char := 16#FFA8#;"},{"id":"5733d26c901662ea","name":"Halfwidth_Hangul_Letter_Thieuth","qualified_name":"Unicode.Names.Half_Full_Withdt_Forms.Halfwidth_Hangul_Letter_Thieuth","kind":"ada_constant","location":{"file":"3rdparty/xmlada/unicode-names-half_full_withdt_forms.ads","line":194,"column":4},"code":"Halfwidth_Hangul_Letter_Thieuth         : constant Unicode_Char := 16#FFBC#;"},{"id":"fb1ee2ff8058340b","name":"Halfwidth_Hangul_Letter_Tikeut","qualified_name":"Unicode.Names.Half_Full_Withdt_Forms.Halfwidth_Hangul_Letter_Tikeut","kind":"ada_constant","location":{"file":"3rdparty/xmlada/unicode-names-half_full_withdt_forms.ads","line":173,"column":4},"code":"Halfwidth_Hangul_Letter_Tikeut          : constant Unicode_Char := 16#FFA7#;"},{"id":"9024ed18a4dae23d","name":"Halfwidth_Hangul_Letter_U","qualified_name":"Unicode.Names.Half_Full_Withdt_Forms.Halfwidth_Hangul_Letter_U","kind":"ada_constant","location":{"file":"3rdparty/xmlada/unicode-names-half_full_withdt_forms.ads","line":210,"column":4},"code":"Halfwidth_Hangul_Letter_U               : constant Unicode_Char := 16#FFD3#;"},{"id":"7d49ccaa8a6918af","name":"Halfwidth_Hangul_Letter_Wa","qualified_name":"Unicode.Names.Half_Full_Withdt_Forms.Halfwidth_Hangul_Letter_Wa","kind":"ada_constant","location":{"file":"3rdparty/xmlada/unicode-names-half_full_withdt_forms.ads","line":206,"column":4},"code":"Halfwidth_Hangul_Letter_Wa              : constant Unicode_Char := 16#FFCD#;"},{"id":"d0243fe59aec6880","name":"Halfwidth_Hangul_Letter_Wae","qualified_name":"Unicode.Names.Half_Full_Withdt_Forms.Halfwidth_Hangul_Letter_Wae","kind":"ada_constant","location":{"file":"3rdparty/xmlada/unicode-names-half_full_withdt_forms.ads","line":207,"column":4},"code":"Halfwidth_Hangul_Letter_Wae             : constant Unicode_Char := 16#FFCE#;"},{"id":"8ff67cccffe59144","name":"Halfwidth_Hangul_Letter_We","qualified_name":"Unicode.Names.Half_Full_Withdt_Forms.Halfwidth_Hangul_Letter_We","kind":"ada_constant","location":{"file":"3rdparty/xmlada/unicode-names-half_full_withdt_forms.ads","line":212,"column":4},"code":"Halfwidth_Hangul_Letter_We              : constant Unicode_Char := 16#FFD5#;"},{"id":"85c32243f9e0e425","name":"Halfwidth_Hangul_Letter_Weo","qualified_name":"Unicode.Names.Half_Full_Withdt_Forms.Halfwidth_Hangul_Letter_Weo","kind":"ada_constant","location":{"file":"3rdparty/xmlada/unicode-names-half_full_withdt_forms.ads","line":211,"column":4},"code":"Halfwidth_Hangul_Letter_Weo             : constant Unicode_Char := 16#FFD4#;"},{"id":"7164d8c813f48d3e","name":"Halfwidth_Hangul_Letter_Wi","qualified_name":"Unicode.Names.Half_Full_Withdt_Forms.Halfwidth_Hangul_Letter_Wi","kind":"ada_constant","location":{"file":"3rdparty/xmlada/unicode-names-half_full_withdt_forms.ads","line":213,"column":4},"code":"Halfwidth_Hangul_Letter_Wi              : constant Unicode_Char := 16#FFD6#;"},{"id":"50b4fcc0482358ed","name":"Halfwidth_Hangul_Letter_Ya","qualified_name":"Unicode.Names.Half_Full_Withdt_Forms.Halfwidth_Hangul_Letter_Ya","kind":"ada_constant","location":{"file":"3rdparty/xmlada/unicode-names-half_full_withdt_forms.ads","line":199,"column":4},"code":"Halfwidth_Hangul_Letter_Ya              : constant Unicode_Char := 16#FFC4#;"},{"id":"74b59f0598a4288a","name":"Halfwidth_Hangul_Letter_Yae","qualified_name":"Unicode.Names.Half_Full_Withdt_Forms.Halfwidth_Hangul_Letter_Yae","kind":"ada_constant","location":{"file":"3rdparty/xmlada/unicode-names-half_full_withdt_forms.ads","line":200,"column":4},"code":"Halfwidth_Hangul_Letter_Yae             : constant Unicode_Char := 16#FFC5#;"},{"id":"4639e7b6a61bf550","name":"Halfwidth_Hangul_Letter_Ye","qualified_name":"Unicode.Names.Half_Full_Withdt_Forms.Halfwidth_Hangul_Letter_Ye","kind":"ada_constant","location":{"file":"3rdparty/xmlada/unicode-names-half_full_withdt_forms.ads","line":204,"column":4},"code":"Halfwidth_Hangul_Letter_Ye              : constant Unicode_Char := 16#FFCB#;"},{"id":"0c4fea8ffda1c8b7","name":"Halfwidth_Hangul_Letter_Yeo","qualified_name":"Unicode.Names.Half_Full_Withdt_Forms.Halfwidth_Hangul_Letter_Yeo","kind":"ada_constant","location":{"file":"3rdparty/xmlada/unicode-names-half_full_withdt_forms.ads","line":203,"column":4},"code":"Halfwidth_Hangul_Letter_Yeo             : constant Unicode_Char := 16#FFCA#;"},{"id":"70c933f5af212c7b","name":"Halfwidth_Hangul_Letter_Yi","qualified_name":"Unicode.Names.Half_Full_Withdt_Forms.Halfwidth_Hangul_Letter_Yi","kind":"ada_constant","location":{"file":"3rdparty/xmlada/unicode-names-half_full_withdt_forms.ads","line":216,"column":4},"code":"Halfwidth_Hangul_Letter_Yi              : constant Unicode_Char := 16#FFDB#;"},{"id":"fabd3f03a6741f61","name":"Halfwidth_Hangul_Letter_Yo","qualified_name":"Unicode.Names.Half_Full_Withdt_Forms.Halfwidth_Hangul_Letter_Yo","kind":"ada_constant","location":{"file":"3rdparty/xmlada/unicode-names-half_full_withdt_forms.ads","line":209,"column":4},"code":"Halfwidth_Hangul_Letter_Yo              : constant Unicode_Char := 16#FFD2#;"},{"id":"8558d8ba3a91816f","name":"Halfwidth_Hangul_Letter_Yu","qualified_name":"Unicode.Names.Half_Full_Withdt_Forms.Halfwidth_Hangul_Letter_Yu","kind":"ada_constant","location":{"file":"3rdparty/xmlada/unicode-names-half_full_withdt_forms.ads","line":214,"column":4},"code":"Halfwidth_Hangul_Letter_Yu              : constant Unicode_Char := 16#FFD7#;"},{"id":"8493db146725546e","name":"Halfwidth_Ideographic_Comma","qualified_name":"Unicode.Names.Half_Full_Withdt_Forms.Halfwidth_Ideographic_Comma","kind":"ada_constant","location":{"file":"3rdparty/xmlada/unicode-names-half_full_withdt_forms.ads","line":104,"column":4},"code":"Halfwidth_Ideographic_Comma             : constant Unicode_Char := 16#FF64#;"},{"id":"a59188995f76e045","name":"Halfwidth_Ideographic_Full_Stop","qualified_name":"Unicode.Names.Half_Full_Withdt_Forms.Halfwidth_Ideographic_Full_Stop","kind":"ada_constant","location":{"file":"3rdparty/xmlada/unicode-names-half_full_withdt_forms.ads","line":101,"column":4},"code":"Halfwidth_Ideographic_Full_Stop         : constant Unicode_Char := 16#FF61#;"},{"id":"f83e762c3cf4dfda","name":"Halfwidth_Katakana_Hiragana_Prolonged_Sound_Mark","qualified_name":"Unicode.Names.Half_Full_Withdt_Forms.Halfwidth_Katakana_Hiragana_Prolonged_Sound_Mark","kind":"ada_constant","location":{"file":"3rdparty/xmlada/unicode-names-half_full_withdt_forms.ads","line":116,"column":4},"code":"Halfwidth_Katakana_Hiragana_Prolonged_Sound_Mark :\n   constant Unicode_Char := 16#FF70#;"},{"id":"8cbb7b217fa04990","name":"Halfwidth_Katakana_Letter_A","qualified_name":"Unicode.Names.Half_Full_Withdt_Forms.Halfwidth_Katakana_Letter_A","kind":"ada_constant","location":{"file":"3rdparty/xmlada/unicode-names-half_full_withdt_forms.ads","line":118,"column":4},"code":"Halfwidth_Katakana_Letter_A             : constant Unicode_Char := 16#FF71#;"},{"id":"f77da91410bb401d","name":"Halfwidth_Katakana_Letter_E","qualified_name":"Unicode.Names.Half_Full_Withdt_Forms.Halfwidth_Katakana_Letter_E","kind":"ada_constant","location":{"file":"3rdparty/xmlada/unicode-names-half_full_withdt_forms.ads","line":121,"column":4},"code":"Halfwidth_Katakana_Letter_E             : constant Unicode_Char := 16#FF74#;"},{"id":"f13ce10994a8b4af","name":"Halfwidth_Katakana_Letter_Ha","qualified_name":"Unicode.Names.Half_Full_Withdt_Forms.Halfwidth_Katakana_Letter_Ha","kind":"ada_constant","location":{"file":"3rdparty/xmlada/unicode-names-half_full_withdt_forms.ads","line":143,"column":4},"code":"Halfwidth_Katakana_Letter_Ha            : constant Unicode_Char := 16#FF8A#;"},{"id":"de2f680b44651850","name":"Halfwidth_Katakana_Letter_He","qualified_name":"Unicode.Names.Half_Full_Withdt_Forms.Halfwidth_Katakana_Letter_He","kind":"ada_constant","location":{"file":"3rdparty/xmlada/unicode-names-half_full_withdt_forms.ads","line":146,"column":4},"code":"Halfwidth_Katakana_Letter_He            : constant Unicode_Char := 16#FF8D#;"},{"id":"64ea2cc2992c141f","name":"Halfwidth_Katakana_Letter_Hi","qualified_name":"Unicode.Names.Half_Full_Withdt_Forms.Halfwidth_Katakana_Letter_Hi","kind":"ada_constant","location":{"file":"3rdparty/xmlada/unicode-names-half_full_withdt_forms.ads","line":144,"column":4},"code":"Halfwidth_Katakana_Letter_Hi            : constant Unicode_Char := 16#FF8B#;"},{"id":"b7956b34bd3adfc7","name":"Halfwidth_Katakana_Letter_Ho","qualified_name":"Unicode.Names.Half_Full_Withdt_Forms.Halfwidth_Katakana_Letter_Ho","kind":"ada_constant","location":{"file":"3rdparty/xmlada/unicode-names-half_full_withdt_forms.ads","line":147,"column":4},"code":"Halfwidth_Katakana_Letter_Ho            : constant Unicode_Char := 16#FF8E#;"},{"id":"aac92093ab5acf9c","name":"Halfwidth_Katakana_Letter_Hu","qualified_name":"Unicode.Names.Half_Full_Withdt_Forms.Halfwidth_Katakana_Letter_Hu","kind":"ada_constant","location":{"file":"3rdparty/xmlada/unicode-names-half_full_withdt_forms.ads","line":145,"column":4},"code":"Halfwidth_Katakana_Letter_Hu            : constant Unicode_Char := 16#FF8C#;"},{"id":"2fff742ac4b6fa6b","name":"Halfwidth_Katakana_Letter_I","qualified_name":"Unicode.Names.Half_Full_Withdt_Forms.Halfwidth_Katakana_Letter_I","kind":"ada_constant","location":{"file":"3rdparty/xmlada/unicode-names-half_full_withdt_forms.ads","line":119,"column":4},"code":"Halfwidth_Katakana_Letter_I             : constant Unicode_Char := 16#FF72#;"},{"id":"7d2c0861e74ff947","name":"Halfwidth_Katakana_Letter_Ka","qualified_name":"Unicode.Names.Half_Full_Withdt_Forms.Halfwidth_Katakana_Letter_Ka","kind":"ada_constant","location":{"file":"3rdparty/xmlada/unicode-names-half_full_withdt_forms.ads","line":123,"column":4},"code":"Halfwidth_Katakana_Letter_Ka            : constant Unicode_Char := 16#FF76#;"},{"id":"817bf1ea5aa1b171","name":"Halfwidth_Katakana_Letter_Ke","qualified_name":"Unicode.Names.Half_Full_Withdt_Forms.Halfwidth_Katakana_Letter_Ke","kind":"ada_constant","location":{"file":"3rdparty/xmlada/unicode-names-half_full_withdt_forms.ads","line":126,"column":4},"code":"Halfwidth_Katakana_Letter_Ke            : constant Unicode_Char := 16#FF79#;"},{"id":"aee4ed33c08d4d10","name":"Halfwidth_Katakana_Letter_Ki","qualified_name":"Unicode.Names.Half_Full_Withdt_Forms.Halfwidth_Katakana_Letter_Ki","kind":"ada_constant","location":{"file":"3rdparty/xmlada/unicode-names-half_full_withdt_forms.ads","line":124,"column":4},"code":"Halfwidth_Katakana_Letter_Ki            : constant Unicode_Char := 16#FF77#;"},{"id":"45e0c85518f56844","name":"Halfwidth_Katakana_Letter_Ko","qualified_name":"Unicode.Names.Half_Full_Withdt_Forms.Halfwidth_Katakana_Letter_Ko","kind":"ada_constant","location":{"file":"3rdparty/xmlada/unicode-names-half_full_withdt_forms.ads","line":127,"column":4},"code":"Halfwidth_Katakana_Letter_Ko            : constant Unicode_Char := 16#FF7A#;"},{"id":"389eaf68d5dd43c6","name":"Halfwidth_Katakana_Letter_Ku","qualified_name":"Unicode.Names.Half_Full_Withdt_Forms.Halfwidth_Katakana_Letter_Ku","kind":"ada_constant","location":{"file":"3rdparty/xmlada/unicode-names-half_full_withdt_forms.ads","line":125,"column":4},"code":"Halfwidth_Katakana_Letter_Ku            : constant Unicode_Char := 16#FF78#;"},{"id":"dc7fb6a8c2a97a98","name":"Halfwidth_Katakana_Letter_Ma","qualified_name":"Unicode.Names.Half_Full_Withdt_Forms.Halfwidth_Katakana_Letter_Ma","kind":"ada_constant","location":{"file":"3rdparty/xmlada/unicode-names-half_full_withdt_forms.ads","line":148,"column":4},"code":"Halfwidth_Katakana_Letter_Ma            : constant Unicode_Char := 16#FF8F#;"},{"id":"0b91f4c999cdf90b","name":"Halfwidth_Katakana_Letter_Me","qualified_name":"Unicode.Names.Half_Full_Withdt_Forms.Halfwidth_Katakana_Letter_Me","kind":"ada_constant","location":{"file":"3rdparty/xmlada/unicode-names-half_full_withdt_forms.ads","line":151,"column":4},"code":"Halfwidth_Katakana_Letter_Me            : constant Unicode_Char := 16#FF92#;"},{"id":"65a52b231884a308","name":"Halfwidth_Katakana_Letter_Mi","qualified_name":"Unicode.Names.Half_Full_Withdt_Forms.Halfwidth_Katakana_Letter_Mi","kind":"ada_constant","location":{"file":"3rdparty/xmlada/unicode-names-half_full_withdt_forms.ads","line":149,"column":4},"code":"Halfwidth_Katakana_Letter_Mi            : constant Unicode_Char := 16#FF90#;"},{"id":"57cd66928340eed7","name":"Halfwidth_Katakana_Letter_Mo","qualified_name":"Unicode.Names.Half_Full_Withdt_Forms.Halfwidth_Katakana_Letter_Mo","kind":"ada_constant","location":{"file":"3rdparty/xmlada/unicode-names-half_full_withdt_forms.ads","line":152,"column":4},"code":"Halfwidth_Katakana_Letter_Mo            : constant Unicode_Char := 16#FF93#;"},{"id":"59edc8a6d4bb5585","name":"Halfwidth_Katakana_Letter_Mu","qualified_name":"Unicode.Names.Half_Full_Withdt_Forms.Halfwidth_Katakana_Letter_Mu","kind":"ada_constant","location":{"file":"3rdparty/xmlada/unicode-names-half_full_withdt_forms.ads","line":150,"column":4},"code":"Halfwidth_Katakana_Letter_Mu            : constant Unicode_Char := 16#FF91#;"},{"id":"c430be2c9fe59e31","name":"Halfwidth_Katakana_Letter_N","qualified_name":"Unicode.Names.Half_Full_Withdt_Forms.Halfwidth_Katakana_Letter_N","kind":"ada_constant","location":{"file":"3rdparty/xmlada/unicode-names-half_full_withdt_forms.ads","line":162,"column":4},"code":"Halfwidth_Katakana_Letter_N             : constant Unicode_Char := 16#FF9D#;"},{"id":"80840cc31d9cabbd","name":"Halfwidth_Katakana_Letter_Na","qualified_name":"Unicode.Names.Half_Full_Withdt_Forms.Halfwidth_Katakana_Letter_Na","kind":"ada_constant","location":{"file":"3rdparty/xmlada/unicode-names-half_full_withdt_forms.ads","line":138,"column":4},"code":"Halfwidth_Katakana_Letter_Na            : constant Unicode_Char := 16#FF85#;"},{"id":"bf1d5afe839b0665","name":"Halfwidth_Katakana_Letter_Ne","qualified_name":"Unicode.Names.Half_Full_Withdt_Forms.Halfwidth_Katakana_Letter_Ne","kind":"ada_constant","location":{"file":"3rdparty/xmlada/unicode-names-half_full_withdt_forms.ads","line":141,"column":4},"code":"Halfwidth_Katakana_Letter_Ne            : constant Unicode_Char := 16#FF88#;"},{"id":"c21009607f09994f","name":"Halfwidth_Katakana_Letter_Ni","qualified_name":"Unicode.Names.Half_Full_Withdt_Forms.Halfwidth_Katakana_Letter_Ni","kind":"ada_constant","location":{"file":"3rdparty/xmlada/unicode-names-half_full_withdt_forms.ads","line":139,"column":4},"code":"Halfwidth_Katakana_Letter_Ni            : constant Unicode_Char := 16#FF86#;"},{"id":"e0ae90bd7f6dbb68","name":"Halfwidth_Katakana_Letter_No","qualified_name":"Unicode.Names.Half_Full_Withdt_Forms.Halfwidth_Katakana_Letter_No","kind":"ada_constant","location":{"file":"3rdparty/xmlada/unicode-names-half_full_withdt_forms.ads","line":142,"column":4},"code":"Halfwidth_Katakana_Letter_No            : constant Unicode_Char := 16#FF89#;"},{"id":"a6180e9ee92f6ce9","name":"Halfwidth_Katakana_Letter_Nu","qualified_name":"Unicode.Names.Half_Full_Withdt_Forms.Halfwidth_Katakana_Letter_Nu","kind":"ada_constant","location":{"file":"3rdparty/xmlada/unicode-names-half_full_withdt_forms.ads","line":140,"column":4},"code":"Halfwidth_Katakana_Letter_Nu            : constant Unicode_Char := 16#FF87#;"},{"id":"b2a10f3154257b10","name":"Halfwidth_Katakana_Letter_O","qualified_name":"Unicode.Names.Half_Full_Withdt_Forms.Halfwidth_Katakana_Letter_O","kind":"ada_constant","location":{"file":"3rdparty/xmlada/unicode-names-half_full_withdt_forms.ads","line":122,"column":4},"code":"Halfwidth_Katakana_Letter_O             : constant Unicode_Char := 16#FF75#;"},{"id":"60cd71913dc9c97c","name":"Halfwidth_Katakana_Letter_Ra","qualified_name":"Unicode.Names.Half_Full_Withdt_Forms.Halfwidth_Katakana_Letter_Ra","kind":"ada_constant","location":{"file":"3rdparty/xmlada/unicode-names-half_full_withdt_forms.ads","line":156,"column":4},"code":"Halfwidth_Katakana_Letter_Ra            : constant Unicode_Char := 16#FF97#;"},{"id":"9bb16338516bfe0a","name":"Halfwidth_Katakana_Letter_Re","qualified_name":"Unicode.Names.Half_Full_Withdt_Forms.Halfwidth_Katakana_Letter_Re","kind":"ada_constant","location":{"file":"3rdparty/xmlada/unicode-names-half_full_withdt_forms.ads","line":159,"column":4},"code":"Halfwidth_Katakana_Letter_Re            : constant Unicode_Char := 16#FF9A#;"},{"id":"87ae114a0c4632b1","name":"Halfwidth_Katakana_Letter_Ri","qualified_name":"Unicode.Names.Half_Full_Withdt_Forms.Halfwidth_Katakana_Letter_Ri","kind":"ada_constant","location":{"file":"3rdparty/xmlada/unicode-names-half_full_withdt_forms.ads","line":157,"column":4},"code":"Halfwidth_Katakana_Letter_Ri            : constant Unicode_Char := 16#FF98#;"},{"id":"6ed9008f24e1d493","name":"Halfwidth_Katakana_Letter_Ro","qualified_name":"Unicode.Names.Half_Full_Withdt_Forms.Halfwidth_Katakana_Letter_Ro","kind":"ada_constant","location":{"file":"3rdparty/xmlada/unicode-names-half_full_withdt_forms.ads","line":160,"column":4},"code":"Halfwidth_Katakana_Letter_Ro            : constant Unicode_Char := 16#FF9B#;"},{"id":"53a84bb67a369614","name":"Halfwidth_Katakana_Letter_Ru","qualified_name":"Unicode.Names.Half_Full_Withdt_Forms.Halfwidth_Katakana_Letter_Ru","kind":"ada_constant","location":{"file":"3rdparty/xmlada/unicode-names-half_full_withdt_forms.ads","line":158,"column":4},"code":"Halfwidth_Katakana_Letter_Ru            : constant Unicode_Char := 16#FF99#;"},{"id":"d1fb0ac602119cb0","name":"Halfwidth_Katakana_Letter_Sa","qualified_name":"Unicode.Names.Half_Full_Withdt_Forms.Halfwidth_Katakana_Letter_Sa","kind":"ada_constant","location":{"file":"3rdparty/xmlada/unicode-names-half_full_withdt_forms.ads","line":128,"column":4},"code":"Halfwidth_Katakana_Letter_Sa            : constant Unicode_Char := 16#FF7B#;"},{"id":"5d3bf83413ea1fd0","name":"Halfwidth_Katakana_Letter_Se","qualified_name":"Unicode.Names.Half_Full_Withdt_Forms.Halfwidth_Katakana_Letter_Se","kind":"ada_constant","location":{"file":"3rdparty/xmlada/unicode-names-half_full_withdt_forms.ads","line":131,"column":4},"code":"Halfwidth_Katakana_Letter_Se            : constant Unicode_Char := 16#FF7E#;"},{"id":"a2764aa93b7c10e2","name":"Halfwidth_Katakana_Letter_Si","qualified_name":"Unicode.Names.Half_Full_Withdt_Forms.Halfwidth_Katakana_Letter_Si","kind":"ada_constant","location":{"file":"3rdparty/xmlada/unicode-names-half_full_withdt_forms.ads","line":129,"column":4},"code":"Halfwidth_Katakana_Letter_Si            : constant Unicode_Char := 16#FF7C#;"},{"id":"63e320a8471f2a5b","name":"Halfwidth_Katakana_Letter_Small_A","qualified_name":"Unicode.Names.Half_Full_Withdt_Forms.Halfwidth_Katakana_Letter_Small_A","kind":"ada_constant","location":{"file":"3rdparty/xmlada/unicode-names-half_full_withdt_forms.ads","line":107,"column":4},"code":"Halfwidth_Katakana_Letter_Small_A       : constant Unicode_Char := 16#FF67#;"},{"id":"b304107bb8c94f22","name":"Halfwidth_Katakana_Letter_Small_E","qualified_name":"Unicode.Names.Half_Full_Withdt_Forms.Halfwidth_Katakana_Letter_Small_E","kind":"ada_constant","location":{"file":"3rdparty/xmlada/unicode-names-half_full_withdt_forms.ads","line":110,"column":4},"code":"Halfwidth_Katakana_Letter_Small_E       : constant Unicode_Char := 16#FF6A#;"},{"id":"0f49f3b276c5e92e","name":"Halfwidth_Katakana_Letter_Small_I","qualified_name":"Unicode.Names.Half_Full_Withdt_Forms.Halfwidth_Katakana_Letter_Small_I","kind":"ada_constant","location":{"file":"3rdparty/xmlada/unicode-names-half_full_withdt_forms.ads","line":108,"column":4},"code":"Halfwidth_Katakana_Letter_Small_I       : constant Unicode_Char := 16#FF68#;"},{"id":"063675a5c3a6ee31","name":"Halfwidth_Katakana_Letter_Small_O","qualified_name":"Unicode.Names.Half_Full_Withdt_Forms.Halfwidth_Katakana_Letter_Small_O","kind":"ada_constant","location":{"file":"3rdparty/xmlada/unicode-names-half_full_withdt_forms.ads","line":111,"column":4},"code":"Halfwidth_Katakana_Letter_Small_O       : constant Unicode_Char := 16#FF6B#;"},{"id":"733c0e81a7429af3","name":"Halfwidth_Katakana_Letter_Small_Tu","qualified_name":"Unicode.Names.Half_Full_Withdt_Forms.Halfwidth_Katakana_Letter_Small_Tu","kind":"ada_constant","location":{"file":"3rdparty/xmlada/unicode-names-half_full_withdt_forms.ads","line":115,"column":4},"code":"Halfwidth_Katakana_Letter_Small_Tu      : constant Unicode_Char := 16#FF6F#;"},{"id":"520f179c942e8d61","name":"Halfwidth_Katakana_Letter_Small_U","qualified_name":"Unicode.Names.Half_Full_Withdt_Forms.Halfwidth_Katakana_Letter_Small_U","kind":"ada_constant","location":{"file":"3rdparty/xmlada/unicode-names-half_full_withdt_forms.ads","line":109,"column":4},"code":"Halfwidth_Katakana_Letter_Small_U       : constant Unicode_Char := 16#FF69#;"},{"id":"533d768ebc69d087","name":"Halfwidth_Katakana_Letter_Small_Ya","qualified_name":"Unicode.Names.Half_Full_Withdt_Forms.Halfwidth_Katakana_Letter_Small_Ya","kind":"ada_constant","location":{"file":"3rdparty/xmlada/unicode-names-half_full_withdt_forms.ads","line":112,"column":4},"code":"Halfwidth_Katakana_Letter_Small_Ya      : constant Unicode_Char := 16#FF6C#;"},{"id":"9aa2f2e086735bfb","name":"Halfwidth_Katakana_Letter_Small_Yo","qualified_name":"Unicode.Names.Half_Full_Withdt_Forms.Halfwidth_Katakana_Letter_Small_Yo","kind":"ada_constant","location":{"file":"3rdparty/xmlada/unicode-names-half_full_withdt_forms.ads","line":114,"column":4},"code":"Halfwidth_Katakana_Letter_Small_Yo      : constant Unicode_Char := 16#FF6E#;"},{"id":"9c27649a59370611","name":"Halfwidth_Katakana_Letter_Small_Yu","qualified_name":"Unicode.Names.Half_Full_Withdt_Forms.Halfwidth_Katakana_Letter_Small_Yu","kind":"ada_constant","location":{"file":"3rdparty/xmlada/unicode-names-half_full_withdt_forms.ads","line":113,"column":4},"code":"Halfwidth_Katakana_Letter_Small_Yu      : constant Unicode_Char := 16#FF6D#;"},{"id":"4f11ff8b54b773c7","name":"Halfwidth_Katakana_Letter_So","qualified_name":"Unicode.Names.Half_Full_Withdt_Forms.Halfwidth_Katakana_Letter_So","kind":"ada_constant","location":{"file":"3rdparty/xmlada/unicode-names-half_full_withdt_forms.ads","line":132,"column":4},"code":"Halfwidth_Katakana_Letter_So            : constant Unicode_Char := 16#FF7F#;"},{"id":"13d2c8b859420186","name":"Halfwidth_Katakana_Letter_Su","qualified_name":"Unicode.Names.Half_Full_Withdt_Forms.Halfwidth_Katakana_Letter_Su","kind":"ada_constant","location":{"file":"3rdparty/xmlada/unicode-names-half_full_withdt_forms.ads","line":130,"column":4},"code":"Halfwidth_Katakana_Letter_Su            : constant Unicode_Char := 16#FF7D#;"},{"id":"1a1afb6a17c91287","name":"Halfwidth_Katakana_Letter_Ta","qualified_name":"Unicode.Names.Half_Full_Withdt_Forms.Halfwidth_Katakana_Letter_Ta","kind":"ada_constant","location":{"file":"3rdparty/xmlada/unicode-names-half_full_withdt_forms.ads","line":133,"column":4},"code":"Halfwidth_Katakana_Letter_Ta            : constant Unicode_Char := 16#FF80#;"},{"id":"b02a2dd5bbaf06d9","name":"Halfwidth_Katakana_Letter_Te","qualified_name":"Unicode.Names.Half_Full_Withdt_Forms.Halfwidth_Katakana_Letter_Te","kind":"ada_constant","location":{"file":"3rdparty/xmlada/unicode-names-half_full_withdt_forms.ads","line":136,"column":4},"code":"Halfwidth_Katakana_Letter_Te            : constant Unicode_Char := 16#FF83#;"},{"id":"393281d2003b9772","name":"Halfwidth_Katakana_Letter_Ti","qualified_name":"Unicode.Names.Half_Full_Withdt_Forms.Halfwidth_Katakana_Letter_Ti","kind":"ada_constant","location":{"file":"3rdparty/xmlada/unicode-names-half_full_withdt_forms.ads","line":134,"column":4},"code":"Halfwidth_Katakana_Letter_Ti            : constant Unicode_Char := 16#FF81#;"},{"id":"06bb73db04f16534","name":"Halfwidth_Katakana_Letter_To","qualified_name":"Unicode.Names.Half_Full_Withdt_Forms.Halfwidth_Katakana_Letter_To","kind":"ada_constant","location":{"file":"3rdparty/xmlada/unicode-names-half_full_withdt_forms.ads","line":137,"column":4},"code":"Halfwidth_Katakana_Letter_To            : constant Unicode_Char := 16#FF84#;"},{"id":"83287db15431f3bd","name":"Halfwidth_Katakana_Letter_Tu","qualified_name":"Unicode.Names.Half_Full_Withdt_Forms.Halfwidth_Katakana_Letter_Tu","kind":"ada_constant","location":{"file":"3rdparty/xmlada/unicode-names-half_full_withdt_forms.ads","line":135,"column":4},"code":"Halfwidth_Katakana_Letter_Tu            : constant Unicode_Char := 16#FF82#;"},{"id":"d84b6fcc93da4fde","name":"Halfwidth_Katakana_Letter_U","qualified_name":"Unicode.Names.Half_Full_Withdt_Forms.Halfwidth_Katakana_Letter_U","kind":"ada_constant","location":{"file":"3rdparty/xmlada/unicode-names-half_full_withdt_forms.ads","line":120,"column":4},"code":"Halfwidth_Katakana_Letter_U             : constant Unicode_Char := 16#FF73#;"},{"id":"6834e515112370fa","name":"Halfwidth_Katakana_Letter_Wa","qualified_name":"Unicode.Names.Half_Full_Withdt_Forms.Halfwidth_Katakana_Letter_Wa","kind":"ada_constant","location":{"file":"3rdparty/xmlada/unicode-names-half_full_withdt_forms.ads","line":161,"column":4},"code":"Halfwidth_Katakana_Letter_Wa            : constant Unicode_Char := 16#FF9C#;"},{"id":"e6b97f8883d74e34","name":"Halfwidth_Katakana_Letter_Wo","qualified_name":"Unicode.Names.Half_Full_Withdt_Forms.Halfwidth_Katakana_Letter_Wo","kind":"ada_constant","location":{"file":"3rdparty/xmlada/unicode-names-half_full_withdt_forms.ads","line":106,"column":4},"code":"Halfwidth_Katakana_Letter_Wo            : constant Unicode_Char := 16#FF66#;"},{"id":"51e8359b254563c6","name":"Halfwidth_Katakana_Letter_Ya","qualified_name":"Unicode.Names.Half_Full_Withdt_Forms.Halfwidth_Katakana_Letter_Ya","kind":"ada_constant","location":{"file":"3rdparty/xmlada/unicode-names-half_full_withdt_forms.ads","line":153,"column":4},"code":"Halfwidth_Katakana_Letter_Ya            : constant Unicode_Char := 16#FF94#;"},{"id":"21a1a202f6f6ee0f","name":"Halfwidth_Katakana_Letter_Yo","qualified_name":"Unicode.Names.Half_Full_Withdt_Forms.Halfwidth_Katakana_Letter_Yo","kind":"ada_constant","location":{"file":"3rdparty/xmlada/unicode-names-half_full_withdt_forms.ads","line":155,"column":4},"code":"Halfwidth_Katakana_Letter_Yo            : constant Unicode_Char := 16#FF96#;"},{"id":"1552d6a385fb3bed","name":"Halfwidth_Katakana_Letter_Yu","qualified_name":"Unicode.Names.Half_Full_Withdt_Forms.Halfwidth_Katakana_Letter_Yu","kind":"ada_constant","location":{"file":"3rdparty/xmlada/unicode-names-half_full_withdt_forms.ads","line":154,"column":4},"code":"Halfwidth_Katakana_Letter_Yu            : constant Unicode_Char := 16#FF95#;"},{"id":"c2c1ccf5ed7b4280","name":"Halfwidth_Katakana_Middle_Dot","qualified_name":"Unicode.Names.Half_Full_Withdt_Forms.Halfwidth_Katakana_Middle_Dot","kind":"ada_constant","location":{"file":"3rdparty/xmlada/unicode-names-half_full_withdt_forms.ads","line":105,"column":4},"code":"Halfwidth_Katakana_Middle_Dot           : constant Unicode_Char := 16#FF65#;"},{"id":"ae46eaaa0df8465e","name":"Halfwidth_Katakana_Semi_Voiced_Sound_Mark","qualified_name":"Unicode.Names.Half_Full_Withdt_Forms.Halfwidth_Katakana_Semi_Voiced_Sound_Mark","kind":"ada_constant","location":{"file":"3rdparty/xmlada/unicode-names-half_full_withdt_forms.ads","line":164,"column":4},"code":"Halfwidth_Katakana_Semi_Voiced_Sound_Mark :\n   constant Unicode_Char := 16#FF9F#;"},{"id":"9ff2451cb53f9ff6","name":"Halfwidth_Katakana_Voiced_Sound_Mark","qualified_name":"Unicode.Names.Half_Full_Withdt_Forms.Halfwidth_Katakana_Voiced_Sound_Mark","kind":"ada_constant","location":{"file":"3rdparty/xmlada/unicode-names-half_full_withdt_forms.ads","line":163,"column":4},"code":"Halfwidth_Katakana_Voiced_Sound_Mark    : constant Unicode_Char := 16#FF9E#;"},{"id":"71eec9af29750a51","name":"Halfwidth_Left_Corner_Bracket","qualified_name":"Unicode.Names.Half_Full_Withdt_Forms.Halfwidth_Left_Corner_Bracket","kind":"ada_constant","location":{"file":"3rdparty/xmlada/unicode-names-half_full_withdt_forms.ads","line":102,"column":4},"code":"Halfwidth_Left_Corner_Bracket           : constant Unicode_Char := 16#FF62#;"},{"id":"4e710a1e7e6f648b","name":"Halfwidth_Leftwards_Arrow","qualified_name":"Unicode.Names.Half_Full_Withdt_Forms.Halfwidth_Leftwards_Arrow","kind":"ada_constant","location":{"file":"3rdparty/xmlada/unicode-names-half_full_withdt_forms.ads","line":226,"column":4},"code":"Halfwidth_Leftwards_Arrow               : constant Unicode_Char := 16#FFE9#;"},{"id":"05e3b2d8c44c8bfb","name":"Halfwidth_Right_Corner_Bracket","qualified_name":"Unicode.Names.Half_Full_Withdt_Forms.Halfwidth_Right_Corner_Bracket","kind":"ada_constant","location":{"file":"3rdparty/xmlada/unicode-names-half_full_withdt_forms.ads","line":103,"column":4},"code":"Halfwidth_Right_Corner_Bracket          : constant Unicode_Char := 16#FF63#;"},{"id":"3416faee8f0a543b","name":"Halfwidth_Rightwards_Arrow","qualified_name":"Unicode.Names.Half_Full_Withdt_Forms.Halfwidth_Rightwards_Arrow","kind":"ada_constant","location":{"file":"3rdparty/xmlada/unicode-names-half_full_withdt_forms.ads","line":228,"column":4},"code":"Halfwidth_Rightwards_Arrow              : constant Unicode_Char := 16#FFEB#;"},{"id":"d49ee9fadb793f6b","name":"Halfwidth_Upwards_Arrow","qualified_name":"Unicode.Names.Half_Full_Withdt_Forms.Halfwidth_Upwards_Arrow","kind":"ada_constant","location":{"file":"3rdparty/xmlada/unicode-names-half_full_withdt_forms.ads","line":227,"column":4},"code":"Halfwidth_Upwards_Arrow                 : constant Unicode_Char := 16#FFEA#;"},{"id":"6076fefc0268ab8a","name":"Halfwidth_White_Circle","qualified_name":"Unicode.Names.Half_Full_Withdt_Forms.Halfwidth_White_Circle","kind":"ada_constant","location":{"file":"3rdparty/xmlada/unicode-names-half_full_withdt_forms.ads","line":231,"column":4},"code":"Halfwidth_White_Circle                  : constant Unicode_Char := 16#FFEE#;"},{"id":"6eceb5c11e7148b2","name":"Zero_Width_No_Break_Space","qualified_name":"Unicode.Names.Half_Full_Withdt_Forms.Zero_Width_No_Break_Space","kind":"ada_constant","location":{"file":"3rdparty/xmlada/unicode-names-half_full_withdt_forms.ads","line":5,"column":4},"code":"Zero_Width_No_Break_Space               : constant Unicode_Char := 16#FEFF#;"}]}